{
  "format": 2,
  "name": {
    "en": "Geoculus"
  },
  "enabled": true,
  "cluster": "off",
  "respawn": "none",
  "icons": {
    "filter": "geoculus",
    "base": {
      "key": "geoculus",
      "iconSize": [34, 32],
      "shadowSize": [50, 64],
      "iconAnchor": [12, 12],
      "shadowAnchor": [4, 62],
      "popupAnchor": [0, -12]
    },
    "done": {
      "key": "geoculus",
      "iconSize": [34, 32],
      "shadowSize": [50, 64],
      "iconAnchor": [12, 12],
      "shadowAnchor": [4, 62],
      "popupAnchor": [0, -12]
    }
  },
  "data": [
    {
      "coordinates": [-27.68353, 33.93677],
      "id": "B27191879C4A126EDE238C67C54A72F218735A66",
      "importIds": {
        "gm_legacy": ["liyueGeoculus/101"]
      },
      "popupTitle": { "en": "#1" },
      "popupAttribution": "Unknown",
      "popupContent": {
        "en": "This Geoculus is UNDERGROUND, you have to complete the Chi of Guyun quest to open the cave and find this Oculus."
      },
      "popupMedia": "https://youtu.be/E8Am0EQASQM"
    },
    {
      "coordinates": [-30.72295, 32.84912],
      "id": "B8ACBB2804CCA0C718602829193A2B0F59666E56",
      "importIds": {
        "gm_legacy": ["liyueGeoculus/102"]
      },
      "popupTitle": { "en": "#2" },
      "popupAttribution": "Unknown",
      "popupMedia": "https://youtu.be/_oISBLhctoQ"
    },
    {
      "coordinates": [-29.91685, 32.59644],
      "id": "BB4653D5E605C5803BB14FA377B44E9445BF3CCD",
      "importIds": {
        "gm_legacy": ["liyueGeoculus/103"]
      },
      "popupTitle": { "en": "#3" },
      "popupAttribution": "Unknown",
      "popupMedia": "https://youtu.be/bBkbX5NdypU"
    },
    {
      "coordinates": [-30.04057, 35.89233],
      "id": "40D371E8D2CB20DAE6C94A02D09BE0AAC14C1EE2",
      "importIds": {
        "gm_legacy": ["liyueGeoculus/104"]
      },
      "popupTitle": { "en": "#4" },
      "popupAttribution": "Unknown",
      "popupMedia": "https://youtu.be/6F1q6aCpU14"
    },
    {
      "coordinates": [-31.25977, 34.29932],
      "id": "487A10FCE6D2710310369A43A558DB0B76689BD6",
      "importIds": {
        "gm_legacy": ["liyueGeoculus/105"]
      },
      "popupTitle": { "en": "#5" },
      "popupAttribution": "Unknown",
      "popupMedia": "https://youtu.be/LBAG5Eew2Uc"
    },
    {
      "coordinates": [-31.93352, 37.13379],
      "id": "F37D436B054D8BB59FD9C446EBA7724FCC3C5553",
      "importIds": {
        "gm_legacy": ["liyueGeoculus/106"]
      },
      "popupTitle": { "en": "#6" },
      "popupAttribution": "Unknown",
      "popupMedia": "https://youtu.be/P1gZD_oojlw"
    },
    {
      "coordinates": [-31.50363, 38.18848],
      "id": "246F4DA76F7D27CEFFB87D9117BDF1F7BD0CF9D6",
      "importIds": {
        "gm_legacy": ["liyueGeoculus/107"]
      },
      "popupTitle": { "en": "#7" },
      "popupAttribution": "Unknown",
      "popupMedia": "https://youtu.be/Hqlcz3_1HOc"
    },
    {
      "coordinates": [-32.06396, 34.96948],
      "id": "D4048A400292B4BFC24D6852810550B6B9A9B0AA",
      "importIds": {
        "gm_legacy": ["liyueGeoculus/108"]
      },
      "popupTitle": { "en": "#8" },
      "popupAttribution": "Unknown",
      "popupMedia": "https://youtu.be/jri_1uDe67c"
    },
    {
      "coordinates": [-32.56533, 32.18994],
      "id": "95DF3797DB8C5ED87CBD68ADCE024E603A84ED4A",
      "importIds": {
        "gm_legacy": ["liyueGeoculus/109"]
      },
      "popupTitle": { "en": "#9" },
      "popupAttribution": "Unknown",
      "popupMedia": "https://youtu.be/m0uoxxgwFE4"
    },
    {
      "coordinates": [-33.07313, 33.76099],
      "id": "9987EB862448719342B1CFA45CE4568E5D12044F",
      "importIds": {
        "gm_legacy": ["liyueGeoculus/110"]
      },
      "popupTitle": { "en": "#10" },
      "popupAttribution": "Unknown",
      "popupMedia": "https://youtu.be/frKU3-5RHP4"
    },
    {
      "coordinates": [-32.92571, 36.52954],
      "id": "90E03BDC9BAD47D448E4295A6A53F09D993A4F65",
      "importIds": {
        "gm_legacy": ["liyueGeoculus/111"]
      },
      "popupTitle": { "en": "#11" },
      "popupAttribution": "Unknown",
      "popupMedia": "https://youtu.be/frKU3-5RHP4"
    },
    {
      "coordinates": [-33.20192, 37.07886],
      "id": "D6BFEE9A57EC2317F3D830BBBC02F51AC957B2AE",
      "importIds": {
        "gm_legacy": ["liyueGeoculus/112"]
      },
      "popupTitle": { "en": "#12" },
      "popupAttribution": "Unknown",
      "popupMedia": "https://youtu.be/7A5eZr2IwN0"
    },
    {
      "coordinates": [-33.2938, 38.60596],
      "id": "F480AC2D48A5D8EEBDFE395CF01F9E2BC2C89615",
      "importIds": {
        "gm_legacy": ["liyueGeoculus/113"]
      },
      "popupTitle": { "en": "#13" },
      "popupAttribution": "Unknown",
      "popupMedia": "https://youtu.be/JcvH4Msr7sE"
    },
    {
      "coordinates": [-34.4341, 36.09009],
      "id": "6024F81A8BE5235D924916057115EB784B47A4A8",
      "importIds": {
        "gm_legacy": ["liyueGeoculus/114"]
      },
      "popupTitle": { "en": "#14" },
      "popupAttribution": "Unknown",
      "popupMedia": "https://youtu.be/hIt-wuV6qR0"
    },
    {
      "coordinates": [-34.16182, 32.00317],
      "id": "EF41E1046748CAB4423E0B07852C9B19C056FA6E",
      "importIds": {
        "gm_legacy": ["liyueGeoculus/115"]
      },
      "popupTitle": { "en": "#15" },
      "popupAttribution": "Unknown",
      "popupMedia": "https://youtu.be/l41ujULyFdQ"
    },
    {
      "coordinates": [-35.37114, 33.46436],
      "id": "086FAC02E4F42983CD37B360EF154C5A45A64403",
      "importIds": {
        "gm_legacy": ["liyueGeoculus/116"]
      },
      "popupTitle": { "en": "#16" },
      "popupAttribution": "Unknown",
      "popupMedia": "https://youtu.be/e7Mg2QVb7IU"
    },
    {
      "coordinates": [-35.08396, 33.9917],
      "id": "29464A48886EE08A60A65E9D488548E69270C9ED",
      "importIds": {
        "gm_legacy": ["liyueGeoculus/117"]
      },
      "popupTitle": { "en": "#17" },
      "popupAttribution": "Unknown",
      "popupMedia": "https://youtu.be/5WaT4WIjzww"
    },
    {
      "coordinates": [-36.02245, 35.8374],
      "id": "10E06F06D53176C1DC83367330BA62367E36F617",
      "importIds": {
        "gm_legacy": ["liyueGeoculus/118"]
      },
      "popupTitle": { "en": "#18" },
      "popupAttribution": "Unknown",
      "popupMedia": "https://youtu.be/f6DYNZqARJA"
    },
    {
      "coordinates": [-37.16907, 35.49683],
      "id": "8F6F9EA2EADEFE93B417CED16225CF6BD220734A",
      "importIds": {
        "gm_legacy": ["liyueGeoculus/119"]
      },
      "popupTitle": { "en": "#19" },
      "popupAttribution": "Unknown",
      "popupMedia": "https://youtu.be/q2AWCQgDNV4"
    },
    {
      "coordinates": [-35.37114, 36.39771],
      "id": "BF836F73E77DD718C516A937D01C2904F018E51F",
      "importIds": {
        "gm_legacy": ["liyueGeoculus/120"]
      },
      "popupTitle": { "en": "#20" },
      "popupAttribution": "Unknown",
      "popupMedia": "https://youtu.be/p7CRiE3COpo"
    },
    {
      "coordinates": [-34.93098, 39.57275],
      "id": "A1CD527776DB80CBB2F5C916C1C3906578D52DFD",
      "importIds": {
        "gm_legacy": ["liyueGeoculus/121"]
      },
      "popupTitle": { "en": "#21" },
      "popupAttribution": "Unknown",
      "popupMedia": "https://youtu.be/eWJ2xfl7F5k"
    },
    {
      "coordinates": [-35.76434, 38.30933],
      "id": "3EE06469F480A2B25095260550D848BA26107779",
      "importIds": {
        "gm_legacy": ["liyueGeoculus/122"]
      },
      "popupTitle": { "en": "#22" },
      "popupAttribution": "Unknown",
      "popupMedia": "https://youtu.be/VQGYXcdGZ6s"
    },
    {
      "coordinates": [-36.57142, 38.15552],
      "id": "53E31BEAF97582BCF510ED24105E6A0F21B0D693",
      "importIds": {
        "gm_legacy": ["liyueGeoculus/123"]
      },
      "popupTitle": { "en": "#23" },
      "popupAttribution": "Unknown",
      "popupMedia": "https://youtu.be/Dr8NtwiE7PA"
    },
    {
      "coordinates": [-37.84016, 38.47412],
      "id": "48CDAACC3DE5171611BC583CA4745E4445C2187C",
      "importIds": {
        "gm_legacy": ["liyueGeoculus/124"]
      },
      "popupTitle": { "en": "#24" },
      "popupAttribution": "Unknown",
      "popupMedia": "https://youtu.be/wEi9tKv1WrQ"
    },
    {
      "coordinates": [-36.27085, 39.52881],
      "id": "E0DF5FBBB435597975DF167B5D720C144C758ACE",
      "importIds": {
        "gm_legacy": ["liyueGeoculus/125"]
      },
      "popupTitle": { "en": "#25" },
      "popupAttribution": "Unknown",
      "popupMedia": "https://youtu.be/27kk3_oo0Y4"
    },
    {
      "coordinates": [-34.61513, 42.12158],
      "id": "8DCB2356252A65259356709467E4632653120841",
      "importIds": {
        "gm_legacy": ["liyueGeoculus/126"]
      },
      "popupTitle": { "en": "#26" },
      "popupAttribution": "Unknown",
      "popupMedia": "https://youtu.be/sS3TeKtq_0w"
    },
    {
      "coordinates": [-37.11653, 40.60547],
      "id": "CCC76D497776D418F7588FEEB925CC5A0CF4F4F9",
      "importIds": {
        "gm_legacy": ["liyueGeoculus/127"]
      },
      "popupTitle": { "en": "#27" },
      "popupAttribution": "Unknown",
      "popupMedia": "https://youtu.be/A1W40-FFaos"
    },
    {
      "coordinates": [-38.1432, 42.02271],
      "id": "6ED439812AD786BCBD7C60440D1FDFB852D806CE",
      "importIds": {
        "gm_legacy": ["liyueGeoculus/128"]
      },
      "popupTitle": { "en": "#28" },
      "popupAttribution": "Unknown",
      "popupMedia": "https://youtu.be/_OPHL0nEjUM"
    },
    {
      "coordinates": [-40.62229, 38.6499],
      "id": "A13FBA855189EA64DD766C9EABEEE04FCC68ECCD",
      "importIds": {
        "gm_legacy": ["liyueGeoculus/129"]
      },
      "popupTitle": { "en": "#29" },
      "popupAttribution": "Unknown",
      "popupMedia": "https://youtu.be/b4neonDG6G8"
    },
    {
      "coordinates": [-39.69873, 36.54053],
      "id": "A5B91295E422188DA97690E86B4EA8AFACE80B9C",
      "importIds": {
        "gm_legacy": ["liyueGeoculus/130"]
      },
      "popupTitle": { "en": "#30" },
      "popupAttribution": "Unknown",
      "popupMedia": "https://youtu.be/Payo3R_KvN8"
    },
    {
      "coordinates": [-38.82259, 46.94458],
      "id": "0ED9EEB79F9696F13922875E3E265DA483E3DBDA",
      "importIds": {
        "gm_legacy": ["liyueGeoculus/131"]
      },
      "popupTitle": { "en": "#31" },
      "popupAttribution": "Unknown",
      "popupMedia": "https://youtu.be/6nCM9Bh0bms"
    },
    {
      "coordinates": [-42.37478, 40.05615],
      "id": "71B7895AC8220FCAB75010504BBEBE5F770ACA1E",
      "importIds": {
        "gm_legacy": ["liyueGeoculus/132"]
      },
      "popupTitle": { "en": "#32" },
      "popupAttribution": "Unknown",
      "popupMedia": "https://youtu.be/s4BG2yCm0-4"
    },
    {
      "coordinates": [-42.30169, 39.59473],
      "id": "7D9B64E595D2072D407C914D96BF6AABFB541776",
      "importIds": {
        "gm_legacy": ["liyueGeoculus/133"]
      },
      "popupTitle": { "en": "#33" },
      "popupAttribution": "Unknown",
      "popupMedia": "https://youtu.be/_dHJCE3ghtc"
    },
    {
      "coordinates": [-42.98858, 40.94604],
      "id": "123122A6CCA5206E727C351BAD8F7C1BCDB4F505",
      "importIds": {
        "gm_legacy": ["liyueGeoculus/134"]
      },
      "popupTitle": { "en": "#34" },
      "popupAttribution": "Unknown",
      "popupMedia": "https://youtu.be/fpDNLbGBB_M"
    },
    {
      "coordinates": [-41.79589, 42.65991],
      "id": "36EDD890692BD3A0BBBAD1DB00162735642188C8",
      "importIds": {
        "gm_legacy": ["liyueGeoculus/135"]
      },
      "popupTitle": { "en": "#35" },
      "popupAttribution": "Unknown",
      "popupMedia": "https://youtu.be/cb6AuN0XtH0"
    },
    {
      "coordinates": [-41.82046, 48.43872],
      "id": "3A1FDD41CADA6F62600385F9AAC737D685A5DA16",
      "importIds": {
        "gm_legacy": ["liyueGeoculus/136"]
      },
      "popupTitle": { "en": "#36" },
      "popupAttribution": "Unknown",
      "popupMedia": "https://youtu.be/qLL2IJohxxY"
    },
    {
      "coordinates": [-42.5045, 47.03247],
      "id": "278B1CC8B572AAA71C674054FF8D1FAA45318B20",
      "importIds": {
        "gm_legacy": ["liyueGeoculus/137"]
      },
      "popupTitle": { "en": "#37" },
      "popupAttribution": "Unknown",
      "popupMedia": "https://youtu.be/Z_PyWFE3_bw"
    },
    {
      "coordinates": [-42.94838, 48.50464],
      "id": "4CB0F94704BE018C4C5258424398C11FD3FF05B3",
      "importIds": {
        "gm_legacy": ["liyueGeoculus/138"]
      },
      "popupTitle": { "en": "#38" },
      "popupAttribution": "Unknown",
      "popupMedia": "https://youtu.be/Ay9wstp-ryM"
    },
    {
      "coordinates": [-43.11702, 46.23047],
      "id": "D84C2A79A2726268220E010C46DF4C8747D919D6",
      "importIds": {
        "gm_legacy": ["liyueGeoculus/139"]
      },
      "popupTitle": { "en": "#39" },
      "popupAttribution": "Unknown",
      "popupMedia": "https://youtu.be/ad9tLw6p-j4"
    },
    {
      "coordinates": [-43.977, 46.08765],
      "id": "3CDE58FC3514613C292DBDD5A32003E14A485170",
      "importIds": {
        "gm_legacy": ["liyueGeoculus/140"]
      },
      "popupTitle": { "en": "#40" },
      "popupAttribution": "Unknown",
      "popupMedia": "https://youtu.be/wi-4J60ey4g"
    },
    {
      "coordinates": [-44.0718, 49.1748],
      "id": "303B345F91D102451856F600CF2477B08323176E",
      "importIds": {
        "gm_legacy": ["liyueGeoculus/141"]
      },
      "popupTitle": { "en": "#41" },
      "popupAttribution": "Unknown",
      "popupMedia": "https://youtu.be/gDSqEBtTCuA"
    },
    {
      "coordinates": [-46.95401, 51.1908],
      "id": "A015310F0D5F9BD412EB36AEA5A02ADB841F7A67",
      "importIds": {
        "gm_legacy": ["liyueGeoculus/142"]
      },
      "popupTitle": { "en": "#42" },
      "popupAttribution": "Unknown",
      "popupMedia": "https://youtu.be/Xw_zZFpvX0Y"
    },
    {
      "coordinates": [-45.78285, 48.21899],
      "id": "A0E5C79A28C8F7D9BC96178AAEE66223E54CDBC3",
      "importIds": {
        "gm_legacy": ["liyueGeoculus/143"]
      },
      "popupTitle": { "en": "#43" },
      "popupAttribution": "Unknown",
      "popupMedia": "https://youtu.be/gMQl7oU7WwU"
    },
    {
      "coordinates": [-44.74673, 51.60278],
      "id": "26FCD3F1028AED5410D6EB6B78522E0FF4C7B5F8",
      "importIds": {
        "gm_legacy": ["liyueGeoculus/144"]
      },
      "popupTitle": { "en": "#44" },
      "popupAttribution": "Unknown",
      "popupMedia": "https://youtu.be/Fsp17ET7yAY"
    },
    {
      "coordinates": [-45.29808, 52.33887],
      "id": "6C6ACD387ECD088FAB47D163D34F91E89ADBA128",
      "importIds": {
        "gm_legacy": ["liyueGeoculus/145"]
      },
      "popupTitle": { "en": "#45" },
      "popupAttribution": "Unknown",
      "popupMedia": "https://youtu.be/TDY2BHRgAhM"
    },
    {
      "coordinates": [-46.7248, 51.60278],
      "id": "9D3E07A3397908FFCC8DB371B655F62BCF08F3C0",
      "importIds": {
        "gm_legacy": ["liyueGeoculus/146"]
      },
      "popupTitle": { "en": "#46" },
      "popupAttribution": "Unknown",
      "popupMedia": "https://youtu.be/0tm5elgCqrw"
    },
    {
      "coordinates": [-47.82053, 47.84546],
      "id": "1A95F5BA1AC08BE46E8C6F436DE074AFB521698A",
      "importIds": {
        "gm_legacy": ["liyueGeoculus/147"]
      },
      "popupTitle": { "en": "#47" },
      "popupAttribution": "Unknown",
      "popupMedia": "https://youtu.be/u05pkN8uXys"
    },
    {
      "coordinates": [-47.53946, 56.14014],
      "id": "EDA505046AF39F1C1C56ADDFA0971E336A253E48",
      "importIds": {
        "gm_legacy": ["liyueGeoculus/148"]
      },
      "popupTitle": { "en": "#48" },
      "popupAttribution": "Unknown",
      "popupContent": {
        "en": "This one is on the island with the chest from the Unswerving achievement."
      },
      "popupMedia": "https://youtu.be/u05pkN8uXys"
    },
    {
      "coordinates": [-52.42252, 53.31665],
      "id": "AE910BE25650DC62BEA010BBD15B08A9E9DF9CE8",
      "importIds": {
        "gm_legacy": ["liyueGeoculus/149"]
      },
      "popupTitle": { "en": "#49" },
      "popupAttribution": "Unknown",
      "popupMedia": "https://youtu.be/ofP8HiSKprY"
    },
    {
      "coordinates": [-52.26816, 58.11768],
      "id": "CE66DF5596E9F3092E7FE4D702A63D2A379196EE",
      "importIds": {
        "gm_legacy": ["liyueGeoculus/150"]
      },
      "popupTitle": { "en": "#50" },
      "popupAttribution": "Unknown",
      "popupMedia": "https://youtu.be/8OKzpVX-8cg"
    },
    {
      "coordinates": [-53.22577, 59.7876],
      "id": "B4B5FB4A348C9353989463C9DC375D5BBDEB55D0",
      "importIds": {
        "gm_legacy": ["liyueGeoculus/151"]
      },
      "popupTitle": { "en": "#51" },
      "popupAttribution": "Unknown",
      "popupMedia": "https://youtu.be/IbVCIy8XkpA"
    },
    {
      "coordinates": [-54.34215, 55.75562],
      "id": "0149BD1E22D1DB3EB2639499FB4C7E1D44B63BCF",
      "importIds": {
        "gm_legacy": ["liyueGeoculus/152"]
      },
      "popupTitle": { "en": "#52" },
      "popupAttribution": "Unknown",
      "popupMedia": "https://youtu.be/2utYOoiE2cc"
    },
    {
      "coordinates": [-44.94147, 44.64844],
      "id": "726FD1328877440EDFC1EB32587C6381883B8F23",
      "importIds": {
        "gm_legacy": ["liyueGeoculus/153"]
      },
      "popupTitle": { "en": "#53" },
      "popupAttribution": "Unknown",
      "popupMedia": "https://youtu.be/ELzDMTpMc3U"
    },
    {
      "coordinates": [-46.03511, 44.05518],
      "id": "2252A601C93F9FC846BAB75D9DBA31AF6AC22C00",
      "importIds": {
        "gm_legacy": ["liyueGeoculus/154"]
      },
      "popupTitle": { "en": "#54" },
      "popupAttribution": "Unknown",
      "popupMedia": "https://youtu.be/bH8yw0rAEd8"
    },
    {
      "coordinates": [-47.01023, 37.99072],
      "id": "54C2FDBA5A372ABADF9C652EA3C7C27F42B7864B",
      "importIds": {
        "gm_legacy": ["liyueGeoculus/155"]
      },
      "popupTitle": { "en": "#55" },
      "popupAttribution": "Unknown",
      "popupMedia": "https://youtu.be/sYHVwmV3-_o"
    },
    {
      "coordinates": [-48.19539, 41.84692],
      "id": "CD4379AC19640944A66DBBA8B51B7A69DA545C5B",
      "importIds": {
        "gm_legacy": ["liyueGeoculus/156"]
      },
      "popupTitle": { "en": "#56" },
      "popupAttribution": "Unknown",
      "popupMedia": "https://youtu.be/Srl6P1a6sm0"
    },
    {
      "coordinates": [-48.84303, 38.17749],
      "id": "4F012F80806840AFD3DC1229EE2026E7EEE6D047",
      "importIds": {
        "gm_legacy": ["liyueGeoculus/157"]
      },
      "popupTitle": { "en": "#57" },
      "popupAttribution": "Unknown",
      "popupMedia": "https://youtu.be/_oGjEK2sEaA"
    },
    {
      "coordinates": [-48.77067, 41.90186],
      "id": "849C4B3062F9C68496E83FE5324B933EBC10DE89",
      "importIds": {
        "gm_legacy": ["liyueGeoculus/158"]
      },
      "popupTitle": { "en": "#58" },
      "popupAttribution": "Unknown",
      "popupMedia": "https://youtu.be/51FVF9MzKrg"
    },
    {
      "coordinates": [-49.08826, 42.96753],
      "id": "EC6D43E4ACDE8ED0D0D45AF08DC662BC9F277D70",
      "importIds": {
        "gm_legacy": ["liyueGeoculus/159"]
      },
      "popupTitle": { "en": "#59" },
      "popupAttribution": "Unknown",
      "popupMedia": "https://youtu.be/ZKueqjkVHUs"
    },
    {
      "coordinates": [-48.84303, 46.51611],
      "id": "6ED37B755FCAA3D09918AB87EC0A93C3555DE1F4",
      "importIds": {
        "gm_legacy": ["liyueGeoculus/160"]
      },
      "popupTitle": { "en": "#60" },
      "popupAttribution": "Unknown",
      "popupMedia": "https://youtu.be/7Padelw800U"
    },
    {
      "coordinates": [-50.1769, 39.9353],
      "id": "7971A05B3071205D6C486F6F26B830094B489201",
      "importIds": {
        "gm_legacy": ["liyueGeoculus/161"]
      },
      "popupTitle": { "en": "#61" },
      "popupAttribution": "Unknown",
      "popupMedia": "https://youtu.be/-dpqT_NWt90"
    },
    {
      "coordinates": [-51.11042, 41.72607],
      "id": "5AACDB4BCD82A005EE2248A446704B229F9DCF2F",
      "importIds": {
        "gm_legacy": ["liyueGeoculus/162"]
      },
      "popupTitle": { "en": "#62" },
      "popupAttribution": "Unknown",
      "popupMedia": "https://youtu.be/UTeR0FQ8It4"
    },
    {
      "coordinates": [-50.94458, 46.97754],
      "id": "99E96B0C6573A885B41429494B54068A06F1F76E",
      "importIds": {
        "gm_legacy": ["liyueGeoculus/163"]
      },
      "popupTitle": { "en": "#63" },
      "popupAttribution": "Unknown",
      "popupMedia": "https://youtu.be/gukEtPqcuA4"
    },
    {
      "coordinates": [-51.85614, 45.46143],
      "id": "ADA80C91B14CDCF12A71F8AF1349803F38FC9481",
      "importIds": {
        "gm_legacy": ["liyueGeoculus/164"]
      },
      "popupTitle": { "en": "#64" },
      "popupAttribution": "Unknown",
      "popupMedia": "https://youtu.be/HLT9FbqmLjc"
    },
    {
      "coordinates": [-53.32431, 38.06763],
      "id": "4653AA7057B5C44CAF94F4A0DDA86C136E9F1F07",
      "importIds": {
        "gm_legacy": ["liyueGeoculus/165"]
      },
      "popupTitle": { "en": "#65" },
      "popupAttribution": "Unknown",
      "popupMedia": "https://youtu.be/iM7Vu_qkIVw"
    },
    {
      "coordinates": [-52.78948, 40.02319],
      "id": "E79AC222A876B0E26CB920F5EA2231369DF22B49",
      "importIds": {
        "gm_legacy": ["liyueGeoculus/166"]
      },
      "popupTitle": { "en": "#66" },
      "popupAttribution": "Unknown",
      "popupMedia": "https://youtu.be/d5k51FMRPG8"
    },
    {
      "coordinates": [-52.47609, 41.33057],
      "id": "59B5D72402A7C0BBD6B454C8AC29070E2CF0A21D",
      "importIds": {
        "gm_legacy": ["liyueGeoculus/167"]
      },
      "popupTitle": { "en": "#67" },
      "popupAttribution": "Unknown",
      "popupMedia": "https://youtu.be/FdngacwvRiM"
    },
    {
      "coordinates": [-50.33845, 34.39819],
      "id": "0A8955018BA8C7742B3EBA28CAB713FF1CEE3652",
      "importIds": {
        "gm_legacy": ["liyueGeoculus/168"]
      },
      "popupTitle": { "en": "#68" },
      "popupAttribution": "Unknown",
      "popupMedia": "https://youtu.be/6FLqwiBfPkc"
    },
    {
      "coordinates": [-48.09276, 34.34326],
      "id": "F343A3916C7D6A19E4238C0E4774118D24528A3C",
      "importIds": {
        "gm_legacy": ["liyueGeoculus/169"]
      },
      "popupTitle": { "en": "#69" },
      "popupAttribution": "Unknown",
      "popupMedia": "https://youtu.be/3yiGWV95dHA"
    },
    {
      "coordinates": [-52.75957, 29.80591],
      "id": "DF42D10833642D7C9210067E1629A796D4E697BC",
      "importIds": {
        "gm_legacy": ["liyueGeoculus/170"]
      },
      "popupTitle": { "en": "#70" },
      "popupAttribution": "Unknown",
      "popupMedia": "https://youtu.be/KYBGLVIv5jA"
    },
    {
      "coordinates": [-52.88902, 31.12427],
      "id": "B73CE74FFCE1FA4CE781AB3479D00A84527FE258",
      "importIds": {
        "gm_legacy": ["liyueGeoculus/171"]
      },
      "popupTitle": { "en": "#71" },
      "popupAttribution": "Unknown",
      "popupMedia": "https://youtu.be/eJeD2J6PwjQ"
    },
    {
      "coordinates": [-52.72964, 31.89331],
      "id": "EC9E9A49771063B66A61256E4F5D1294FE888CD0",
      "importIds": {
        "gm_legacy": ["liyueGeoculus/172"]
      },
      "popupTitle": { "en": "#72" },
      "popupAttribution": "Unknown",
      "popupMedia": "https://youtu.be/ce5rmzezcX4"
    },
    {
      "coordinates": [-53.48805, 26.80115],
      "id": "70ED2ABFC8D7A264B70A85AD9A3C06D8C935543F",
      "importIds": {
        "gm_legacy": ["liyueGeoculus/173"]
      },
      "popupTitle": { "en": "#73" },
      "popupAttribution": "Unknown",
      "popupMedia": "https://youtu.be/30_rGj-Ey2o"
    },
    {
      "coordinates": [-54.29729, 28.25684],
      "id": "B11BED80E038507D161E1FA125076E7EAEC7A3FA",
      "importIds": {
        "gm_legacy": ["liyueGeoculus/174"]
      },
      "popupTitle": { "en": "#74" },
      "popupAttribution": "Unknown",
      "popupMedia": "https://youtu.be/fdjh_vpIEgE"
    },
    {
      "coordinates": [-55.71473, 26.38916],
      "id": "D39531FAE5CC4887D4FFF72D1B6169DDF71A3B68",
      "importIds": {
        "gm_legacy": ["liyueGeoculus/175"]
      },
      "popupTitle": { "en": "#75" },
      "popupAttribution": "Unknown",
      "popupMedia": "https://youtu.be/8Y7uYeknUBg"
    },
    {
      "coordinates": [-56.03523, 29.10278],
      "id": "F5CB3D9731FF6DE2550CC38188CF4A0BFF41F6A0",
      "importIds": {
        "gm_legacy": ["liyueGeoculus/176"]
      },
      "popupTitle": { "en": "#76" },
      "popupAttribution": "Unknown",
      "popupMedia": "https://youtu.be/--s1JgO07GE"
    },
    {
      "coordinates": [-56.79486, 26.18042],
      "id": "F8450BAE046468320468872FF60BF67682190385",
      "importIds": {
        "gm_legacy": ["liyueGeoculus/177"]
      },
      "popupTitle": { "en": "#77" },
      "popupAttribution": "Unknown",
      "popupMedia": "https://youtu.be/gZG2wHny7ho"
    },
    {
      "coordinates": [-55.67139, 32.12402],
      "id": "79BC8C66750F9CE8D33D2833D7DF180F026454C0",
      "importIds": {
        "gm_legacy": ["liyueGeoculus/178"]
      },
      "popupTitle": { "en": "#78" },
      "popupAttribution": "Unknown",
      "popupMedia": "https://youtu.be/-d_Ut55rxLw"
    },
    {
      "coordinates": [-54.92714, 36.34277],
      "id": "53E977C06140C05CFFFF13C4D37E7A379A0E9715",
      "importIds": {
        "gm_legacy": ["liyueGeoculus/179"]
      },
      "popupTitle": { "en": "#79" },
      "popupAttribution": "Unknown",
      "popupMedia": "https://youtu.be/_gDVa1v-jvA"
    },
    {
      "coordinates": [-55.12865, 35.71655],
      "id": "E18B6EF921C2A895AF41A37FD141D2913834D835",
      "importIds": {
        "gm_legacy": ["liyueGeoculus/180"]
      },
      "popupTitle": { "en": "#80" },
      "popupAttribution": "Unknown",
      "popupMedia": "https://youtu.be/HFAXa5jLRT0"
    },
    {
      "coordinates": [-55.86298, 35.77148],
      "id": "EC8C0F00F9840A6779959540F1725648A8738883",
      "importIds": {
        "gm_legacy": ["liyueGeoculus/181"]
      },
      "popupTitle": { "en": "#81" },
      "popupAttribution": "Unknown",
      "popupMedia": "https://youtu.be/e6zWmirYLUw"
    },
    {
      "coordinates": [-56.39566, 34.76074],
      "id": "EAF4E2E8A6F4FE5E624E1CE5A5319601B6BA8947",
      "importIds": {
        "gm_legacy": ["liyueGeoculus/182"]
      },
      "popupTitle": { "en": "#82" },
      "popupAttribution": "Unknown",
      "popupMedia": "https://youtu.be/pXwdxI22Y-k"
    },
    {
      "coordinates": [-57.07657, 37.03491],
      "id": "E448D6F338D45C6AEE2C9B63A6018331F9151668",
      "importIds": {
        "gm_legacy": ["liyueGeoculus/183"]
      },
      "popupTitle": { "en": "#83" },
      "popupAttribution": "Unknown",
      "popupMedia": "https://youtu.be/tTICslXMqQ4"
    },
    {
      "coordinates": [-57.73348, 37.55676],
      "id": "2A215E7BE57A357FD7DDDE221199A5D01A6D3ABD",
      "importIds": {
        "gm_legacy": ["liyueGeoculus/184"]
      },
      "popupTitle": { "en": "#84" },
      "popupAttribution": "Unknown",
      "popupContent": {
        "en": "There is a small cave underneath the statue; the entrance is covered by foliage."
      },
      "popupMedia": "https://youtu.be/VWj0_BUjOuk"
    },
    {
      "coordinates": [-58.41322, 33.49731],
      "id": "B5ABB3B8EB3D735AFE0F9F7A49D33808FD691E18",
      "importIds": {
        "gm_legacy": ["liyueGeoculus/185"]
      },
      "popupTitle": { "en": "#85" },
      "popupAttribution": "Unknown",
      "popupMedia": "https://youtu.be/TSEFDAiZHyQ"
    },
    {
      "coordinates": [-58.3902, 31.26709],
      "id": "36472CA8BF0D1E574023BB316BF85EBF74576BCC",
      "importIds": {
        "gm_legacy": ["liyueGeoculus/186"]
      },
      "popupTitle": { "en": "#86" },
      "popupAttribution": "Unknown",
      "popupMedia": "https://youtu.be/Zk7rlyDZ8eU"
    },
    {
      "coordinates": [-58.61978, 26.37817],
      "id": "65EAAF8CFB76E7467AE01F53AA8713B6DE0FD318",
      "importIds": {
        "gm_legacy": ["liyueGeoculus/187"]
      },
      "popupTitle": { "en": "#87" },
      "popupAttribution": "Unknown",
      "popupMedia": "https://youtu.be/avPznFh1zxk"
    },
    {
      "coordinates": [-49.88048, 24.01611],
      "id": "337695E8ACA4008C52B0617BB274DE1E73B1D514",
      "importIds": {
        "gm_legacy": ["liyueGeoculus/188"]
      },
      "popupTitle": { "en": "#88" },
      "popupAttribution": "Unknown",
      "popupMedia": "https://youtu.be/LWJMVqsBeIQ"
    },
    {
      "coordinates": [-48.57479, 23.90625],
      "id": "1477B91D89FE585AF5A88809CFF6904710B16919",
      "importIds": {
        "gm_legacy": ["liyueGeoculus/189"]
      },
      "popupTitle": { "en": "#89" },
      "popupAttribution": "Unknown",
      "popupMedia": "https://youtu.be/hK8loD5l0S4"
    },
    {
      "coordinates": [-34.26176, 27.97119],
      "id": "08D5BBA9C8BFFD850E850382F1BF4819E5DEA1C7",
      "importIds": {
        "gm_legacy": ["liyueGeoculus/190"]
      },
      "popupTitle": { "en": "#90" },
      "popupAttribution": "Unknown",
      "popupMedia": "https://youtu.be/N3bRA1s90YQ"
    },
    {
      "coordinates": [-36.25313, 25.88379],
      "id": "54789C55070C3ECEBB2FED83A871BAAB2A30AA8D",
      "importIds": {
        "gm_legacy": ["liyueGeoculus/191"]
      },
      "popupTitle": { "en": "#91" },
      "popupAttribution": "Unknown",
      "popupMedia": "https://youtu.be/-MBQykDN_io"
    },
    {
      "coordinates": [-36.78289, 26.77368],
      "id": "7199DBB3B558405F065E0E551F960589F453A5B9",
      "importIds": {
        "gm_legacy": ["liyueGeoculus/192"]
      },
      "popupTitle": { "en": "#92" },
      "popupAttribution": "Unknown",
      "popupMedia": "https://youtu.be/dLqK34fv2r4"
    },
    {
      "coordinates": [-36.52729, 29.90479],
      "id": "D15CC9365023581AE625DB57891E6B4E80232C63",
      "importIds": {
        "gm_legacy": ["liyueGeoculus/193"]
      },
      "popupTitle": { "en": "#93" },
      "popupAttribution": "Unknown",
      "popupMedia": "https://youtu.be/MKhJGbjT3As"
    },
    {
      "coordinates": [-38.72838, 26.00464],
      "id": "66A916F6988A60396EDC6F68CE306BD2AEF3B139",
      "importIds": {
        "gm_legacy": ["liyueGeoculus/194"]
      },
      "popupTitle": { "en": "#94" },
      "popupAttribution": "Unknown",
      "popupMedia": "https://youtu.be/hyqEurczc4U"
    },
    {
      "coordinates": [-39.43619, 31.82739],
      "id": "FEA279AFDAC34554D054E92C539F29971501104A",
      "importIds": {
        "gm_legacy": ["liyueGeoculus/195"]
      },
      "popupTitle": { "en": "#95" },
      "popupAttribution": "Unknown",
      "popupMedia": "https://youtu.be/oL5PQc__t-8"
    },
    {
      "coordinates": [-43.61222, 37.27661],
      "id": "FC14F9547A25F8F3ABB6060461F919C25C3DCD72",
      "importIds": {
        "gm_legacy": ["liyueGeoculus/196"]
      },
      "popupTitle": { "en": "#96" },
      "popupAttribution": "Unknown",
      "popupMedia": "https://youtu.be/qvHN2rmTj7A"
    },
    {
      "coordinates": [-43.14909, 35.354],
      "id": "4C5836F1DAA0EA1B0785F64FCD09A3AE15A7A287",
      "importIds": {
        "gm_legacy": ["liyueGeoculus/197"]
      },
      "popupTitle": { "en": "#97" },
      "popupAttribution": "Unknown",
      "popupMedia": "https://youtu.be/-bvFk5NcUDw"
    },
    {
      "coordinates": [-47.44295, 32.95898],
      "id": "8F03ED73A0C2D4350B7D14A68B75DF668CFDB2D0",
      "importIds": {
        "gm_legacy": ["liyueGeoculus/198"]
      },
      "popupTitle": { "en": "#98" },
      "popupAttribution": "Unknown",
      "popupMedia": "https://youtu.be/KXJAHCqbWSA"
    },
    {
      "coordinates": [-45.26715, 32.34375],
      "id": "3A3CFA0F1A2737A198C0190FE91C60225E7CF3F0",
      "importIds": {
        "gm_legacy": ["liyueGeoculus/199"]
      },
      "popupTitle": { "en": "#99" },
      "popupAttribution": "Unknown",
      "popupMedia": "https://youtu.be/eWs35HkCn8A"
    },
    {
      "coordinates": [-56.98091, 47.59277],
      "id": "3E48C9ADFA2D31B99806D0D895616CEFC59413E4",
      "importIds": {
        "gm_legacy": ["liyueGeoculus/200"]
      },
      "popupTitle": { "en": "#100" },
      "popupAttribution": "Unknown",
      "popupMedia": "https://youtu.be/INxp5VJXQQg"
    },
    {
      "coordinates": [-43.61222, 31.10229],
      "id": "2CCE6ABDCDF548DF0C188A8AFCF6DCCC60CE0FC2",
      "importIds": {
        "gm_legacy": ["liyueGeoculus/201"]
      },
      "popupTitle": { "en": "#101" },
      "popupAttribution": "Unknown",
      "popupMedia": "https://youtu.be/Wrloz2mfQ2k"
    },
    {
      "coordinates": [-45.058, 29.23462],
      "id": "A78C4935693381E8F268697040794EB579C64DAF",
      "importIds": {
        "gm_legacy": ["liyueGeoculus/202"]
      },
      "popupTitle": { "en": "#102" },
      "popupAttribution": "Unknown",
      "popupMedia": "https://youtu.be/rdDBPxpy1r0"
    },
    {
      "coordinates": [-45.82114, 27.79541],
      "id": "E089A8549DE82EE110D4A2F3EBB56995EDD6680B",
      "importIds": {
        "gm_legacy": ["liyueGeoculus/203"]
      },
      "popupTitle": { "en": "#103" },
      "popupAttribution": "Unknown",
      "popupMedia": "https://youtu.be/CwVA8PHdpXU"
    },
    {
      "coordinates": [-44.94925, 26.58691],
      "id": "8DC7E9177197132A3EBCC1421D8F3E66E8489ED4",
      "importIds": {
        "gm_legacy": ["liyueGeoculus/204"]
      },
      "popupTitle": { "en": "#104" },
      "popupAttribution": "Unknown",
      "popupMedia": "https://youtu.be/-QuBn6A1mwM"
    },
    {
      "coordinates": [-44.06391, 27.18018],
      "id": "4E3BD534981F824E0A9FA0B1AD2ADE45117A61B3",
      "importIds": {
        "gm_legacy": ["liyueGeoculus/205"]
      },
      "popupTitle": { "en": "#105" },
      "popupAttribution": "Unknown",
      "popupMedia": "https://youtu.be/9mgBKTXisGY"
    },
    {
      "coordinates": [-44.1822, 26.09253],
      "id": "99433605E99C2896CBA7DAE1F0FC684F1A2C412E",
      "importIds": {
        "gm_legacy": ["liyueGeoculus/206"]
      },
      "popupTitle": { "en": "#106" },
      "popupAttribution": "Unknown",
      "popupMedia": "https://youtu.be/bWevd8RHjOI"
    },
    {
      "coordinates": [-43.77903, 25.78491],
      "id": "C0A406B66E44C43F74536362658DC328920BABD3",
      "importIds": {
        "gm_legacy": ["liyueGeoculus/207"]
      },
      "popupTitle": { "en": "#107" },
      "popupAttribution": "Unknown",
      "popupMedia": "https://youtu.be/_7FsPnXKluE"
    },
    {
      "coordinates": [-45.213, 24.64233],
      "id": "98BED822338C41764F3DE6B1D3E3C20B708AB46F",
      "importIds": {
        "gm_legacy": ["liyueGeoculus/208"]
      },
      "popupTitle": { "en": "#108" },
      "popupAttribution": "Unknown",
      "popupMedia": "https://youtu.be/qSNqjNxZUns"
    },
    {
      "coordinates": [-43.02071, 24.07104],
      "id": "F6E271B05055FC72DC00B46AE1A448D92321CAE8",
      "importIds": {
        "gm_legacy": ["liyueGeoculus/209"]
      },
      "popupTitle": { "en": "#109" },
      "popupAttribution": "Unknown",
      "popupMedia": "https://youtu.be/v7RC6BNfIlk"
    },
    {
      "coordinates": [-41.82046, 26.70776],
      "id": "B8361312920550734892DB75523CEFD2D5489F07",
      "importIds": {
        "gm_legacy": ["liyueGeoculus/210"]
      },
      "popupTitle": { "en": "#110" },
      "popupAttribution": "Unknown",
      "popupMedia": "https://youtu.be/eZqEoVE_Uyk"
    },
    {
      "coordinates": [-40.9716, 27.3999],
      "id": "20ACC64BB46C88B5889BB96B017105DAEB23A076",
      "importIds": {
        "gm_legacy": ["liyueGeoculus/211"]
      },
      "popupTitle": { "en": "#111" },
      "popupAttribution": "Unknown",
      "popupMedia": "https://youtu.be/8Zj11TdoflY"
    },
    {
      "coordinates": [-41.36032, 25.65308],
      "id": "0B727FF00059066B47264109A02BABCC8A6C165E",
      "importIds": {
        "gm_legacy": ["liyueGeoculus/212"]
      },
      "popupTitle": { "en": "#112" },
      "popupAttribution": "Unknown",
      "popupMedia": "https://youtu.be/kzKlHKPN_JY"
    },
    {
      "coordinates": [-38.53098, 21.698],
      "id": "7AED399CD7BE0E8F0F3A64C92AFE0AF8E0B3B5DF",
      "importIds": {
        "gm_legacy": ["liyueGeoculus/213"]
      },
      "popupTitle": { "en": "#113" },
      "popupAttribution": "Unknown",
      "popupMedia": "https://youtu.be/EWpyq7taw70"
    },
    {
      "coordinates": [-40.12009, 20.91797],
      "id": "9155E08767C990DBB620CAD8EF08C52E5D52B2C5",
      "importIds": {
        "gm_legacy": ["liyueGeoculus/214"]
      },
      "popupTitle": { "en": "#114" },
      "popupAttribution": "Unknown",
      "popupMedia": "https://youtu.be/OdJrH11MstQ"
    },
    {
      "coordinates": [-41.55792, 21.34644],
      "id": "D26FE02DED25A44C99A2CA1623E82EB0F89C719B",
      "importIds": {
        "gm_legacy": ["liyueGeoculus/215"]
      },
      "popupTitle": { "en": "#115" },
      "popupAttribution": "Unknown",
      "popupMedia": "https://youtu.be/HDrijgc5chQ"
    },
    {
      "coordinates": [-41.70573, 19.47876],
      "id": "DD00CD34AFCD41EE66AAC4EB7388ADF3B19EA495",
      "importIds": {
        "gm_legacy": ["liyueGeoculus/216"]
      },
      "popupTitle": { "en": "#116" },
      "popupAttribution": "Unknown",
      "popupMedia": "https://youtu.be/b-VlK5bCbMU"
    },
    {
      "coordinates": [-41.91863, 20.83008],
      "id": "3E5FD1690C6E73F7E6B2D2ECC50FAE7909AF60F2",
      "importIds": {
        "gm_legacy": ["liyueGeoculus/217"]
      },
      "popupTitle": { "en": "#117" },
      "popupAttribution": "Unknown",
      "popupMedia": "https://youtu.be/A33d-uYDy4w"
    },
    {
      "coordinates": [-42.17155, 21.43433],
      "id": "993807AA4146371F493517559D59B6AF3A62D4D3",
      "importIds": {
        "gm_legacy": ["liyueGeoculus/218"]
      },
      "popupTitle": { "en": "#118" },
      "popupAttribution": "Unknown",
      "popupMedia": "https://youtu.be/HINlGcuI0Yw"
    },
    {
      "coordinates": [-42.45589, 22.40112],
      "id": "98C6959A86D1C151C65B6E4082E0E9E8E3D6BBA1",
      "importIds": {
        "gm_legacy": ["liyueGeoculus/219"]
      },
      "popupTitle": { "en": "#119" },
      "popupAttribution": "Unknown",
      "popupMedia": "https://youtu.be/26a6XtrfdEA"
    },
    {
      "coordinates": [-44.00862, 19.25903],
      "id": "5E21EDBD5D864898FD360BD592A7E382FCEA2FC8",
      "importIds": {
        "gm_legacy": ["liyueGeoculus/220"]
      },
      "popupTitle": { "en": "#120" },
      "popupAttribution": "Unknown",
      "popupMedia": "https://youtu.be/wnhzkj3nMus"
    },
    {
      "coordinates": [-43.63608, 17.96265],
      "id": "7A5D5D6A21C946C5EB1E9252E18F10088B59D6D6",
      "importIds": {
        "gm_legacy": ["liyueGeoculus/221"]
      },
      "popupTitle": { "en": "#121" },
      "popupAttribution": "Unknown",
      "popupMedia": "https://youtu.be/_CbP7zK1p-I"
    },
    {
      "coordinates": [-44.8948, 17.8418],
      "id": "6D4D39BC66F6EDDA3D7D258B027E9B0002211D34",
      "importIds": {
        "gm_legacy": ["liyueGeoculus/222"]
      },
      "popupTitle": { "en": "#122" },
      "popupAttribution": "Unknown",
      "popupMedia": "https://youtu.be/gnOttevqAYw"
    },
    {
      "coordinates": [-44.72332, 18.56689],
      "id": "4A11A9BBB343D269932A471D866238CA85D2EC35",
      "importIds": {
        "gm_legacy": ["liyueGeoculus/223"]
      },
      "popupTitle": { "en": "#123" },
      "popupAttribution": "Unknown",
      "popupMedia": "https://youtu.be/yVXUvfXJpNg"
    },
    {
      "coordinates": [-44.27667, 20.28076],
      "id": "6A323D7A033910EC13B512FDBF4D02B98FA5EE91",
      "importIds": {
        "gm_legacy": ["liyueGeoculus/224"]
      },
      "popupTitle": { "en": "#124" },
      "popupAttribution": "Unknown",
      "popupMedia": "https://youtu.be/2_zn_27kXT8"
    },
    {
      "coordinates": [-44.27667, 20.64331],
      "id": "358417A797CD3480D41C2C1340D9083F2FA3BDA6",
      "importIds": {
        "gm_legacy": ["liyueGeoculus/225"]
      },
      "popupTitle": { "en": "#125" },
      "popupAttribution": "Unknown",
      "popupMedia": "https://youtu.be/e_lxSXnGMCE"
    },
    {
      "coordinates": [-38.5997, 39.78149],
      "id": "9EE135ED5133C70197D4A5DA9C1A272712CB2520",
      "importIds": {
        "gm_legacy": ["liyueGeoculus/226"]
      },
      "popupTitle": { "en": "#126" },
      "popupAttribution": "Unknown",
      "popupMedia": "https://youtu.be/5jQqUsNVnEo"
    },
    {
      "coordinates": [-45.56022, 48.91113],
      "id": "BCE60A0B97E037FA9BC9203AB16FE1A617A57C31",
      "importIds": {
        "gm_legacy": ["liyueGeoculus/227"]
      },
      "popupTitle": { "en": "#127" },
      "popupAttribution": "Unknown",
      "popupMedia": "https://youtu.be/D8gqdZ6btCg"
    },
    {
      "coordinates": [-44.04812, 35.05737],
      "id": "8291B6DEE9F640F4658DE0D91E375469BD3551B8",
      "importIds": {
        "gm_legacy": ["liyueGeoculus/228"]
      },
      "popupTitle": { "en": "#128" },
      "popupAttribution": "Unknown",
      "popupMedia": "https://youtu.be/e4KUM1dKhLY"
    },
    {
      "coordinates": [-37.32649, 30.9375],
      "id": "B6B0F7EDF2F79F7993B5A0F09F8B42E6F7246A35",
      "importIds": {
        "gm_legacy": ["liyueGeoculus/229"]
      },
      "popupTitle": { "en": "#129" },
      "popupAttribution": "Unknown",
      "popupMedia": "https://youtu.be/p8JcfckJhZg"
    },
    {
      "coordinates": [-54.83866, 61.67725],
      "id": "7BF20AE5709A173DAA5FD9242BE9D9F3FFC688BD",
      "importIds": {
        "gm_legacy": ["liyueGeoculus/230"]
      },
      "popupTitle": { "en": "#130" },
      "popupAttribution": "Unknown",
      "popupMedia": "https://youtu.be/4-X6mVEOlVc"
    },
    {
      "coordinates": [-42.24479, 36.87012],
      "id": "F79EB0045C7413A039D04491D73693CA3334C654",
      "importIds": {
        "gm_legacy": ["liyueGeoculus/231"]
      },
      "popupTitle": { "en": "#131" },
      "popupAttribution": "Unknown",
      "popupMedia": "https://youtu.be/a_GtgEQLE50"
    }
  ]
}
