{
  "name": { "en": "Crimson Agate" },
  "cluster": false,
  "icons": {
    "filter": "crimson-agate",
    "base": {
      "key": "oculus",
      "svg": true,
      "iconSize": [24, 24],
      "shadowSize": [50, 64],
      "iconAnchor": [12, 12],
      "shadowAnchor": [4, 62],
      "popupAnchor": [0, -12]
    },
    "done": {
      "key": "oculus",
      "svg": true,
      "iconSize": [24, 24],
      "shadowSize": [50, 64],
      "iconAnchor": [12, 12],
      "shadowAnchor": [4, 62],
      "popupAnchor": [0, -12]
    }
  },
  "data": []
}
