{
  "format": 2,
  "description": {
    "en": "The stamen of a fiercely burning flower. Harvest using a Hydro skill. Used in Alchemy."
  },
  "enabled": true,
  "cluster": "on",
  "name": {
    "en": "Flaming Flower Stamen",
    "pt": "Flor Flamejante (Estame)",
    "ru": "Пылающий Цветок (тычинка)"
  },
  "respawn": 172800,
  "icons": {
    "filter": "flaming-flower-stamen",
    "base": {
      "marker": true
    },
    "done": {
      "marker": true
    }
  },
  "data": [
    {
      "coordinates": [-33.6625, 19.38438],
      "id": "3242007C2EEFB713EAA7D8D3D88C4528A9CFC13E",
      "importIds": {
        "gm_legacy": ["liyueFlamingFlowerStamen/1"],
        "yuanshen": ["52_1"]
      },
      "popupTitle": {
        "zh": "烈焰花"
      },
      "popupContent": {
        "zh": "这是一朵烈焰花"
      },
      "popupAttribution": "Yuanshen.site"
    },
    {
      "coordinates": [-33.696, 19.47681],
      "id": "3C85626657AC55C749DB2D4F7410E3BFA3DE8E29",
      "importIds": {
        "gm_legacy": ["liyueFlamingFlowerStamen/2"],
        "yuanshen": ["52_2"]
      },
      "popupTitle": {
        "zh": "烈焰花"
      },
      "popupContent": {
        "zh": "这是一朵烈焰花"
      },
      "popupAttribution": "Yuanshen.site"
    },
    {
      "coordinates": [-33.71257, 19.47681],
      "id": "63A989142FDEB2068B5A263517C0592E258BB2E4",
      "importIds": {
        "gm_legacy": ["liyueFlamingFlowerStamen/3"],
        "yuanshen": ["52_3"]
      },
      "popupTitle": {
        "zh": "烈焰花"
      },
      "popupContent": {
        "zh": "这是一朵烈焰花"
      },
      "popupAttribution": "Yuanshen.site"
    },
    {
      "coordinates": [-29.56415, 29.23898],
      "id": "15D4022E735B1875829047D1581A479A5D92BD0D",
      "importIds": {
        "gm_legacy": ["liyueFlamingFlowerStamen/4"],
        "yuanshen": ["52_4"]
      },
      "popupTitle": {
        "zh": "烈焰花"
      },
      "popupContent": {
        "zh": "这是一朵烈焰花"
      },
      "popupAttribution": "Yuanshen.site"
    },
    {
      "coordinates": [-34.30248, 16.16111],
      "id": "7F1B2121EB541483D2EC19A860537DB46FE81C8A",
      "importIds": {
        "yuanshen": ["52_5"]
      },
      "popupTitle": {
        "zh": "烈焰花"
      },
      "popupContent": {
        "zh": "这是一朵烈焰花"
      },
      "popupAttribution": "Yuanshen.site"
    },
    {
      "coordinates": [-32.22419, 34.09061],
      "id": "28E1C1DEF4316E2D104359714E870C68D57090F2",
      "importIds": {
        "yuanshen": ["52_6"]
      },
      "popupTitle": {
        "zh": "烈焰花"
      },
      "popupContent": {
        "zh": "这是一朵烈焰花"
      },
      "popupAttribution": "Yuanshen.site"
    },
    {
      "coordinates": [-32.99843, 32.21965],
      "id": "E57AEB2D49C80FF0995943D6F6FB90C6F8783A99",
      "importIds": {
        "yuanshen": ["52_7"]
      },
      "popupTitle": {
        "zh": "烈焰花"
      },
      "popupContent": {
        "zh": "这是一朵烈焰花"
      },
      "popupAttribution": "Yuanshen.site"
    },
    {
      "coordinates": [-38.04922, 23.09185],
      "id": "0286B31A6D15F7144B80F425E7DB42B0C6493A0A",
      "importIds": {
        "yuanshen": ["52_8"]
      },
      "popupTitle": {
        "zh": "烈焰花"
      },
      "popupContent": {
        "zh": "这是一朵烈焰花"
      },
      "popupAttribution": "Yuanshen.site"
    },
    {
      "coordinates": [-43.81006, 41.32377],
      "id": "6B87AF07AFFBD5D1EB32ED69247DF582DD2CEF95",
      "importIds": {
        "yuanshen": ["52_9"]
      },
      "popupTitle": {
        "zh": "烈焰花"
      },
      "popupContent": {
        "zh": "这是一朵烈焰花"
      },
      "popupAttribution": "Yuanshen.site"
    },
    {
      "coordinates": [-45.82599, 41.25204],
      "id": "6E00CEA0923F8C4384A61B4B3B7D99F60A7709D7",
      "importIds": {
        "yuanshen": ["52_10"]
      },
      "popupTitle": {
        "zh": "烈焰花"
      },
      "popupContent": {
        "zh": "这是一朵烈焰花"
      },
      "popupAttribution": "Yuanshen.site"
    },
    {
      "coordinates": [-37.62734, 36.13178],
      "id": "B43FD635FA60F7136B3FA6FD1425BF18CB1FF8B2",
      "importIds": {
        "yuanshen": ["52_11"]
      },
      "popupTitle": {
        "zh": "烈焰花"
      },
      "popupContent": {
        "zh": "这是一朵烈焰花"
      },
      "popupAttribution": "Yuanshen.site"
    },
    {
      "coordinates": [-38.48412, 30.22337],
      "id": "BC3A3B9C1EEB36F87FED4CAE3460E0904EB6E092",
      "importIds": {
        "yuanshen": ["52_12"]
      },
      "popupTitle": {
        "zh": "烈焰花"
      },
      "popupContent": {
        "zh": "这是一朵烈焰花"
      },
      "popupAttribution": "Yuanshen.site"
    },
    {
      "coordinates": [-40.81972, 20.39394],
      "id": "C76135AB0630C5F0EAD7471B601556FCED4F9A07",
      "importIds": {
        "yuanshen": ["52_13"]
      },
      "popupTitle": {
        "zh": "烈焰花"
      },
      "popupContent": {
        "zh": "这是一朵烈焰花"
      },
      "popupAttribution": "Yuanshen.site"
    },
    {
      "coordinates": [-40.82005, 20.43646],
      "id": "7FCB9CE0C7FA0A61277212E3976A2EA5C1C401EE",
      "importIds": {
        "yuanshen": ["52_14"]
      },
      "popupTitle": {
        "zh": "烈焰花"
      },
      "popupContent": {
        "zh": "这是一朵烈焰花"
      },
      "popupAttribution": "Yuanshen.site"
    },
    {
      "coordinates": [-40.77708, 20.41042],
      "id": "ED5FBAF15283A75D70D028C1706B76A20017D8B9",
      "importIds": {
        "yuanshen": ["52_15"]
      },
      "popupTitle": {
        "zh": "烈焰花"
      },
      "popupContent": {
        "zh": "这是一朵烈焰花"
      },
      "popupAttribution": "Yuanshen.site"
    },
    {
      "coordinates": [-25.99062, 27.88178],
      "id": "EAB255276A0ADCF05038F4A7241569C10A7E6AD5",
      "importIds": {
        "yuanshen": ["52_16"]
      },
      "popupTitle": {
        "zh": "烈焰花"
      },
      "popupContent": {
        "zh": "这是一朵烈焰花"
      },
      "popupAttribution": "Yuanshen.site"
    },
    {
      "coordinates": [-25.95935, 27.88177],
      "id": "596B2996160E769F58D5A0EC31C02C5BAA39279C",
      "importIds": {
        "yuanshen": ["52_17"]
      },
      "popupTitle": {
        "zh": "烈焰花"
      },
      "popupContent": {
        "zh": "这是一朵烈焰花"
      },
      "popupAttribution": "Yuanshen.site"
    },
    {
      "coordinates": [-25.92423, 27.89996],
      "id": "07A3C4C6A54441BC68464864056E103338D4B9E7",
      "importIds": {
        "yuanshen": ["52_18"]
      },
      "popupTitle": {
        "zh": "烈焰花"
      },
      "popupContent": {
        "zh": "这是一朵烈焰花"
      },
      "popupAttribution": "Yuanshen.site"
    },
    {
      "coordinates": [-40.45025, 22.69557],
      "id": "DF6EFCDF06BFB955F96EE759A0620AEB0FBC1D74",
      "importIds": {
        "yuanshen": ["52_19"]
      },
      "popupTitle": {
        "zh": "烈焰花"
      },
      "popupContent": {
        "zh": "这是一朵烈焰花"
      },
      "popupAttribution": "Yuanshen.site"
    },
    {
      "coordinates": [-40.36172, 22.6474],
      "id": "7D2A16E8B498664B27520936CCA1EFC381567689",
      "importIds": {
        "yuanshen": ["52_20"]
      },
      "popupTitle": {
        "zh": "烈焰花"
      },
      "popupContent": {
        "zh": "这是一朵烈焰花"
      },
      "popupAttribution": "Yuanshen.site"
    },
    {
      "coordinates": [-40.37865, 22.33229],
      "id": "30A3A9EDFE4B24AE38F21A3D73802111A437882F",
      "importIds": {
        "yuanshen": ["52_21"]
      },
      "popupTitle": {
        "zh": "烈焰花"
      },
      "popupContent": {
        "zh": "这是一朵烈焰花"
      },
      "popupAttribution": "Yuanshen.site"
    },
    {
      "coordinates": [-35.21978, 35.60443],
      "id": "F4209F91331E506685718CB4B309B8CF86A30BEC",
      "importIds": {
        "yuanshen": ["52_22"]
      },
      "popupTitle": {
        "zh": "烈焰花"
      },
      "popupContent": {
        "zh": "这是一朵烈焰花"
      },
      "popupAttribution": "Yuanshen.site"
    }
  ]
}
