{
  "name": { "en": "Violetgrass" },
  "cluster": false,
  "respawn": 172800,
  "icons": {
    "filter": "violetgrass",
    "base": {
      "marker": true
    },
    "done": {
      "marker": true
    }
  },
  "data": [
    {
      "geometry": {
        "type": "Point",
        "coordinates": [-36.6684189189, 48.6145019531]
      },
      "type": "Feature",
      "properties": {
        "popupTitle": { "en": "" },
        "popupContent": { "en": "" },
        "popupMedia": ""
      },
      "id": 1
    },
    {
      "geometry": {
        "type": "Point",
        "coordinates": [-36.8884080431, 48.076171875]
      },
      "type": "Feature",
      "properties": {
        "popupTitle": { "en": "" },
        "popupContent": { "en": "" },
        "popupMedia": ""
      },
      "id": 2
    },
    {
      "geometry": {
        "type": "Point",
        "coordinates": [-37.011325943, 47.900390625]
      },
      "type": "Feature",
      "properties": {
        "popupTitle": { "en": "" },
        "popupContent": { "en": "" },
        "popupMedia": ""
      },
      "id": 3
    },
    {
      "geometry": {
        "type": "Point",
        "coordinates": [-36.923547681, 47.7355957031]
      },
      "type": "Feature",
      "properties": {
        "popupTitle": { "en": "" },
        "popupContent": { "en": "" },
        "popupMedia": ""
      },
      "id": 4
    },
    {
      "geometry": {
        "type": "Point",
        "coordinates": [-37.0185957448, 47.7685546875]
      },
      "type": "Feature",
      "properties": {
        "popupTitle": { "en": "" },
        "popupContent": { "en": "" },
        "popupMedia": ""
      },
      "id": 6
    },
    {
      "geometry": {
        "type": "Point",
        "coordinates": [-37.1324985804, 49.1967773437]
      },
      "type": "Feature",
      "properties": {
        "popupTitle": { "en": "" },
        "popupContent": { "en": "" },
        "popupMedia": ""
      },
      "id": 7
    },
    {
      "geometry": {
        "type": "Point",
        "coordinates": [-40.2166354753, 48.345336914]
      },
      "type": "Feature",
      "properties": {
        "popupTitle": { "en": "" },
        "popupContent": { "en": "" },
        "popupMedia": ""
      },
      "id": 8
    },
    {
      "geometry": {
        "type": "Point",
        "coordinates": [-40.2863820248, 48.2739257812]
      },
      "type": "Feature",
      "properties": {
        "popupTitle": { "en": "" },
        "popupContent": { "en": "" },
        "popupMedia": ""
      },
      "id": 9
    },
    {
      "geometry": {
        "type": "Point",
        "coordinates": [-40.3758437769, 47.8729248046]
      },
      "type": "Feature",
      "properties": {
        "popupTitle": { "en": "" },
        "popupContent": { "en": "" },
        "popupMedia": ""
      },
      "id": 10
    },
    {
      "geometry": {
        "type": "Point",
        "coordinates": [-40.7222826728, 47.7465820312]
      },
      "type": "Feature",
      "properties": {
        "popupTitle": { "en": "" },
        "popupContent": { "en": "" },
        "popupMedia": ""
      },
      "id": 11
    },
    {
      "geometry": {
        "type": "Point",
        "coordinates": [-42.4275113263, 46.0491943359]
      },
      "type": "Feature",
      "properties": {
        "popupTitle": { "en": "" },
        "popupContent": { "en": "" },
        "popupMedia": ""
      },
      "id": 12
    },
    {
      "geometry": {
        "type": "Point",
        "coordinates": [-43.2743120735, 46.6259765625]
      },
      "type": "Feature",
      "properties": {
        "popupTitle": { "en": "" },
        "popupContent": { "en": "" },
        "popupMedia": ""
      },
      "id": 13
    },
    {
      "geometry": {
        "type": "Point",
        "coordinates": [-43.7042983323, 45.9887695312]
      },
      "type": "Feature",
      "properties": {
        "popupTitle": { "en": "" },
        "popupContent": { "en": "" },
        "popupMedia": ""
      },
      "id": 14
    },
    {
      "geometry": {
        "type": "Point",
        "coordinates": [-43.1140891395, 48.5595703125]
      },
      "type": "Feature",
      "properties": {
        "popupTitle": { "en": "" },
        "popupContent": { "en": "" },
        "popupMedia": ""
      },
      "id": 15
    },
    {
      "geometry": {
        "type": "Point",
        "coordinates": [-44.5571313565, 50.537109375]
      },
      "type": "Feature",
      "properties": {
        "popupTitle": { "en": "" },
        "popupContent": { "en": "" },
        "popupMedia": ""
      },
      "id": 17
    },
    {
      "geometry": {
        "type": "Point",
        "coordinates": [-44.9605140671, 50.888671875]
      },
      "type": "Feature",
      "properties": {
        "popupTitle": { "en": "" },
        "popupContent": { "en": "" },
        "popupMedia": ""
      },
      "id": 18
    },
    {
      "geometry": {
        "type": "Point",
        "coordinates": [-45.732095275, 48.076171875]
      },
      "type": "Feature",
      "properties": {
        "popupTitle": { "en": "" },
        "popupContent": { "en": "" },
        "popupMedia": ""
      },
      "id": 19
    },
    {
      "geometry": {
        "type": "Point",
        "coordinates": [-45.6946698435, 49.8999023437]
      },
      "type": "Feature",
      "properties": {
        "popupTitle": { "en": "" },
        "popupContent": { "en": "" },
        "popupMedia": ""
      },
      "id": 20
    },
    {
      "geometry": {
        "type": "Point",
        "coordinates": [-45.9309282545, 49.3725585937]
      },
      "type": "Feature",
      "properties": {
        "popupTitle": { "en": "" },
        "popupContent": { "en": "" },
        "popupMedia": ""
      },
      "id": 21
    },
    {
      "geometry": {
        "type": "Point",
        "coordinates": [-45.8976545343, 46.5106201171]
      },
      "type": "Feature",
      "properties": {
        "popupTitle": { "en": "" },
        "popupContent": { "en": "" },
        "popupMedia": ""
      },
      "id": 22
    },
    {
      "geometry": {
        "type": "Point",
        "coordinates": [-52.0380203631, 54.931640625]
      },
      "type": "Feature",
      "properties": {
        "popupTitle": { "en": "" },
        "popupContent": { "en": "" },
        "popupMedia": ""
      },
      "id": 23
    },
    {
      "geometry": {
        "type": "Point",
        "coordinates": [-51.9559778923, 54.755859375]
      },
      "type": "Feature",
      "properties": {
        "popupTitle": { "en": "" },
        "popupContent": { "en": "" },
        "popupMedia": ""
      },
      "id": 24
    },
    {
      "geometry": {
        "type": "Point",
        "coordinates": [-33.3067892308, 32.9813911341]
      },
      "type": "Feature",
      "properties": {
        "popupTitle": { "en": "" },
        "popupContent": { "en": "" },
        "popupMedia": ""
      },
      "id": 25
    },
    {
      "geometry": {
        "type": "Point",
        "coordinates": [-34.0071283976, 32.9644753786]
      },
      "type": "Feature",
      "properties": {
        "popupTitle": { "en": "" },
        "popupContent": { "en": "" },
        "popupMedia": ""
      },
      "id": 26
    },
    {
      "geometry": {
        "type": "Point",
        "coordinates": [-36.372644996, 36.3757324218]
      },
      "type": "Feature",
      "properties": {
        "popupTitle": { "en": "" },
        "popupContent": { "en": "" },
        "popupMedia": ""
      },
      "id": 27
    },
    {
      "geometry": {
        "type": "Point",
        "coordinates": [-36.4477991295, 36.4636230468]
      },
      "type": "Feature",
      "properties": {
        "popupTitle": { "en": "" },
        "popupContent": { "en": "" },
        "popupMedia": ""
      },
      "id": 28
    },
    {
      "geometry": {
        "type": "Point",
        "coordinates": [-36.3062721695, 36.4471435546]
      },
      "type": "Feature",
      "properties": {
        "popupTitle": { "en": "" },
        "popupContent": { "en": "" },
        "popupMedia": ""
      },
      "id": 29
    },
    {
      "geometry": {
        "type": "Point",
        "coordinates": [-36.3770678398, 36.5295410156]
      },
      "type": "Feature",
      "properties": {
        "popupTitle": { "en": "" },
        "popupContent": { "en": "" },
        "popupMedia": ""
      },
      "id": 30
    },
    {
      "geometry": {
        "type": "Point",
        "coordinates": [-35.8356283888, 38.3422851562]
      },
      "type": "Feature",
      "properties": {
        "popupTitle": { "en": "" },
        "popupContent": { "en": "" },
        "popupMedia": ""
      },
      "id": 32
    },
    {
      "geometry": {
        "type": "Point",
        "coordinates": [-35.777714272, 38.4466552734]
      },
      "type": "Feature",
      "properties": {
        "popupTitle": { "en": "" },
        "popupContent": { "en": "" },
        "popupMedia": ""
      },
      "id": 33
    },
    {
      "geometry": {
        "type": "Point",
        "coordinates": [-34.9084578539, 39.4573974609]
      },
      "type": "Feature",
      "properties": {
        "popupTitle": { "en": "" },
        "popupContent": { "en": "" },
        "popupMedia": ""
      },
      "id": 34
    },
    {
      "geometry": {
        "type": "Point",
        "coordinates": [-35.0165009958, 39.4354248046]
      },
      "type": "Feature",
      "properties": {
        "popupTitle": { "en": "" },
        "popupContent": { "en": "" },
        "popupMedia": ""
      },
      "id": 35
    },
    {
      "geometry": {
        "type": "Point",
        "coordinates": [-35.029996369, 39.3310546875]
      },
      "type": "Feature",
      "properties": {
        "popupTitle": { "en": "" },
        "popupContent": { "en": "" },
        "popupMedia": ""
      },
      "id": 36
    },
    {
      "geometry": {
        "type": "Point",
        "coordinates": [-34.9264749358, 39.3365478515]
      },
      "type": "Feature",
      "properties": {
        "popupTitle": { "en": "" },
        "popupContent": { "en": "" },
        "popupMedia": ""
      },
      "id": 37
    },
    {
      "geometry": {
        "type": "Point",
        "coordinates": [-35.7152980121, 38.3532714843]
      },
      "type": "Feature",
      "properties": {
        "popupTitle": { "en": "" },
        "popupContent": { "en": "" },
        "popupMedia": ""
      },
      "id": 38
    },
    {
      "geometry": {
        "type": "Point",
        "coordinates": [-34.2799143985, 35.9088134765]
      },
      "type": "Feature",
      "properties": {
        "popupTitle": { "en": "" },
        "popupContent": { "en": "" },
        "popupMedia": ""
      },
      "id": 40
    },
    {
      "geometry": {
        "type": "Point",
        "coordinates": [-34.5699063808, 37.3260498046]
      },
      "type": "Feature",
      "properties": {
        "popupTitle": { "en": "" },
        "popupContent": { "en": "" },
        "popupMedia": ""
      },
      "id": 41
    },
    {
      "geometry": {
        "type": "Point",
        "coordinates": [-37.1603165467, 24.7631835937]
      },
      "type": "Feature",
      "properties": {
        "popupTitle": { "en": "" },
        "popupContent": { "en": "" },
        "popupMedia": ""
      },
      "id": 42
    },
    {
      "geometry": {
        "type": "Point",
        "coordinates": [-37.1428034437, 24.7082519531]
      },
      "type": "Feature",
      "properties": {
        "popupTitle": { "en": "" },
        "popupContent": { "en": "" },
        "popupMedia": ""
      },
      "id": 43
    },
    {
      "geometry": {
        "type": "Point",
        "coordinates": [-37.0551771066, 24.7521972656]
      },
      "type": "Feature",
      "properties": {
        "popupTitle": { "en": "" },
        "popupContent": { "en": "" },
        "popupMedia": ""
      },
      "id": 44
    },
    {
      "geometry": {
        "type": "Point",
        "coordinates": [-41.9594900989, 21.796875]
      },
      "type": "Feature",
      "properties": {
        "popupTitle": { "en": "" },
        "popupContent": { "en": "" },
        "popupMedia": ""
      },
      "id": 45
    },
    {
      "geometry": {
        "type": "Point",
        "coordinates": [-41.8450126727, 21.97265625]
      },
      "type": "Feature",
      "properties": {
        "popupTitle": { "en": "" },
        "popupContent": { "en": "" },
        "popupMedia": ""
      },
      "id": 46
    },
    {
      "geometry": {
        "type": "Point",
        "coordinates": [-41.9921602333, 22.0495605468]
      },
      "type": "Feature",
      "properties": {
        "popupTitle": { "en": "" },
        "popupContent": { "en": "" },
        "popupMedia": ""
      },
      "id": 47
    },
    {
      "geometry": {
        "type": "Point",
        "coordinates": [-44.2294565683, 20.2368164062]
      },
      "type": "Feature",
      "properties": {
        "popupTitle": { "en": "" },
        "popupContent": { "en": "" },
        "popupMedia": ""
      },
      "id": 48
    },
    {
      "geometry": {
        "type": "Point",
        "coordinates": [-44.2215837654, 20.4565429687]
      },
      "type": "Feature",
      "properties": {
        "popupTitle": { "en": "" },
        "popupContent": { "en": "" },
        "popupMedia": ""
      },
      "id": 49
    },
    {
      "geometry": {
        "type": "Point",
        "coordinates": [-47.9991279925, 34.5040185291]
      },
      "type": "Feature",
      "properties": {
        "popupTitle": { "en": "" },
        "popupContent": { "en": "" },
        "popupMedia": ""
      },
      "id": 50
    },
    {
      "geometry": {
        "type": "Point",
        "coordinates": [-48.1859250849, 34.5972406145]
      },
      "type": "Feature",
      "properties": {
        "popupTitle": { "en": "" },
        "popupContent": { "en": "" },
        "popupMedia": ""
      },
      "id": 51
    },
    {
      "geometry": {
        "type": "Point",
        "coordinates": [-47.9678587799, 34.3212890625]
      },
      "type": "Feature",
      "properties": {
        "popupTitle": { "en": "" },
        "popupContent": { "en": "" },
        "popupMedia": ""
      },
      "id": 52
    },
    {
      "geometry": {
        "type": "Point",
        "coordinates": [-48.0340191586, 34.3322753906]
      },
      "type": "Feature",
      "properties": {
        "popupTitle": { "en": "" },
        "popupContent": { "en": "" },
        "popupMedia": ""
      },
      "id": 53
    },
    {
      "geometry": {
        "type": "Point",
        "coordinates": [-48.2393089902, 34.2114257812]
      },
      "type": "Feature",
      "properties": {
        "popupTitle": { "en": "" },
        "popupContent": { "en": "" },
        "popupMedia": ""
      },
      "id": 54
    },
    {
      "geometry": {
        "type": "Point",
        "coordinates": [-52.961875059, 27.6086425781]
      },
      "type": "Feature",
      "properties": {
        "popupTitle": { "en": "" },
        "popupContent": { "en": "" },
        "popupMedia": ""
      },
      "id": 55
    },
    {
      "geometry": {
        "type": "Point",
        "coordinates": [-54.0658357716, 31.0913085937]
      },
      "type": "Feature",
      "properties": {
        "popupTitle": { "en": "" },
        "popupContent": { "en": "" },
        "popupMedia": ""
      },
      "id": 56
    },
    {
      "geometry": {
        "type": "Point",
        "coordinates": [-54.463652645, 31.6625976562]
      },
      "type": "Feature",
      "properties": {
        "popupTitle": { "en": "" },
        "popupContent": { "en": "" },
        "popupMedia": ""
      },
      "id": 57
    },
    {
      "geometry": {
        "type": "Point",
        "coordinates": [-54.5210814954, 30.6958007812]
      },
      "type": "Feature",
      "properties": {
        "popupTitle": { "en": "" },
        "popupContent": { "en": "" },
        "popupMedia": ""
      },
      "id": 58
    },
    {
      "geometry": {
        "type": "Point",
        "coordinates": [-54.6229781326, 30.5639648437]
      },
      "type": "Feature",
      "properties": {
        "popupTitle": { "en": "" },
        "popupContent": { "en": "" },
        "popupMedia": ""
      },
      "id": 59
    },
    {
      "geometry": {
        "type": "Point",
        "coordinates": [-54.5274574994, 30.8386230468]
      },
      "type": "Feature",
      "properties": {
        "popupTitle": { "en": "" },
        "popupContent": { "en": "" },
        "popupMedia": ""
      },
      "id": 60
    },
    {
      "geometry": {
        "type": "Point",
        "coordinates": [-55.1982097596, 31.1169494259]
      },
      "type": "Feature",
      "properties": {
        "popupTitle": { "en": "" },
        "popupContent": { "en": "" },
        "popupMedia": ""
      },
      "id": 61
    },
    {
      "geometry": {
        "type": "Point",
        "coordinates": [-55.6566599076, 26.6422893262]
      },
      "type": "Feature",
      "properties": {
        "popupTitle": { "en": "" },
        "popupContent": { "en": "" },
        "popupMedia": ""
      },
      "id": 62
    },
    {
      "geometry": {
        "type": "Point",
        "coordinates": [-55.8926062399, 26.564604255]
      },
      "type": "Feature",
      "properties": {
        "popupTitle": { "en": "" },
        "popupContent": { "en": "" },
        "popupMedia": ""
      },
      "id": 63
    },
    {
      "geometry": {
        "type": "Point",
        "coordinates": [-56.0404331467, 26.7199743974]
      },
      "type": "Feature",
      "properties": {
        "popupTitle": { "en": "" },
        "popupContent": { "en": "" },
        "popupMedia": ""
      },
      "id": 64
    },
    {
      "geometry": {
        "type": "Point",
        "coordinates": [-56.474628058, 27.4877929687]
      },
      "type": "Feature",
      "properties": {
        "popupTitle": { "en": "" },
        "popupContent": { "en": "" },
        "popupMedia": ""
      },
      "id": 65
    },
    {
      "geometry": {
        "type": "Point",
        "coordinates": [-56.5836917212, 29.8498535156]
      },
      "type": "Feature",
      "properties": {
        "popupTitle": { "en": "" },
        "popupContent": { "en": "" },
        "popupMedia": ""
      },
      "id": 66
    },
    {
      "geometry": {
        "type": "Point",
        "coordinates": [-56.5291991401, 30.0256347656]
      },
      "type": "Feature",
      "properties": {
        "popupTitle": { "en": "" },
        "popupContent": { "en": "" },
        "popupMedia": ""
      },
      "id": 67
    },
    {
      "geometry": {
        "type": "Point",
        "coordinates": [-55.4850790375, 34.3981933593]
      },
      "type": "Feature",
      "properties": {
        "popupTitle": { "en": "" },
        "popupContent": { "en": "" },
        "popupMedia": ""
      },
      "id": 68
    },
    {
      "geometry": {
        "type": "Point",
        "coordinates": [-56.2182473141, 32.4206542968]
      },
      "type": "Feature",
      "properties": {
        "popupTitle": { "en": "" },
        "popupContent": { "en": "" },
        "popupMedia": ""
      },
      "id": 69
    },
    {
      "geometry": {
        "type": "Point",
        "coordinates": [-56.2792211482, 32.5744628906]
      },
      "type": "Feature",
      "properties": {
        "popupTitle": { "en": "" },
        "popupContent": { "en": "" },
        "popupMedia": ""
      },
      "id": 70
    },
    {
      "geometry": {
        "type": "Point",
        "coordinates": [-56.1816163871, 32.607421875]
      },
      "type": "Feature",
      "properties": {
        "popupTitle": { "en": "" },
        "popupContent": { "en": "" },
        "popupMedia": ""
      },
      "id": 71
    },
    {
      "geometry": {
        "type": "Point",
        "coordinates": [-56.0653875114, 32.9040527343]
      },
      "type": "Feature",
      "properties": {
        "popupTitle": { "en": "" },
        "popupContent": { "en": "" },
        "popupMedia": ""
      },
      "id": 72
    },
    {
      "geometry": {
        "type": "Point",
        "coordinates": [-56.1327207153, 33.1237792968]
      },
      "type": "Feature",
      "properties": {
        "popupTitle": { "en": "" },
        "popupContent": { "en": "" },
        "popupMedia": ""
      },
      "id": 73
    },
    {
      "geometry": {
        "type": "Point",
        "coordinates": [-42.1796881966, 48.076171875]
      },
      "type": "Feature",
      "properties": {
        "popupTitle": { "en": "" },
        "popupContent": { "en": "" },
        "popupMedia": ""
      },
      "id": 74
    },
    {
      "geometry": {
        "type": "Point",
        "coordinates": [-44.2215837654, 45.9228515625]
      },
      "type": "Feature",
      "properties": {
        "popupTitle": { "en": "" },
        "popupContent": { "en": "" },
        "popupMedia": ""
      },
      "id": 75
    },
    {
      "geometry": {
        "type": "Point",
        "coordinates": [-45.1897800966, 46.9006347656]
      },
      "type": "Feature",
      "properties": {
        "popupTitle": { "en": "" },
        "popupContent": { "en": "" },
        "popupMedia": ""
      },
      "id": 76
    },
    {
      "geometry": {
        "type": "Point",
        "coordinates": [-45.7636909566, 47.4554443359]
      },
      "type": "Feature",
      "properties": {
        "popupTitle": { "en": "" },
        "popupContent": { "en": "" },
        "popupMedia": ""
      },
      "id": 77
    },
    {
      "geometry": {
        "type": "Point",
        "coordinates": [-45.5986656898, 49.048461914]
      },
      "type": "Feature",
      "properties": {
        "popupTitle": { "en": "" },
        "popupContent": { "en": "" },
        "popupMedia": ""
      },
      "id": 78
    },
    {
      "geometry": {
        "type": "Point",
        "coordinates": [-45.3405631388, 49.0704345703]
      },
      "type": "Feature",
      "properties": {
        "popupTitle": { "en": "" },
        "popupContent": { "en": "" },
        "popupMedia": ""
      },
      "id": 79
    },
    {
      "geometry": {
        "type": "Point",
        "coordinates": [-44.1546224307, 50.806274414]
      },
      "type": "Feature",
      "properties": {
        "popupTitle": { "en": "" },
        "popupContent": { "en": "" },
        "popupMedia": ""
      },
      "id": 80
    },
    {
      "geometry": {
        "type": "Point",
        "coordinates": [-42.7187681026, 46.2139892578]
      },
      "type": "Feature",
      "properties": {
        "popupTitle": { "en": "" },
        "popupContent": { "en": "" },
        "popupMedia": ""
      },
      "id": 81
    },
    {
      "geometry": {
        "type": "Point",
        "coordinates": [-42.5449866731, 46.0437011718]
      },
      "type": "Feature",
      "properties": {
        "popupTitle": { "en": "" },
        "popupContent": { "en": "" },
        "popupMedia": ""
      },
      "id": 82
    },
    {
      "geometry": {
        "type": "Point",
        "coordinates": [-40.3758437769, 47.8729248046]
      },
      "type": "Feature",
      "properties": {
        "popupTitle": { "en": "" },
        "popupContent": { "en": "" },
        "popupMedia": ""
      },
      "id": 83
    },
    {
      "geometry": {
        "type": "Point",
        "coordinates": [-40.7472569628, 46.9830322265]
      },
      "type": "Feature",
      "properties": {
        "popupTitle": { "en": "" },
        "popupContent": { "en": "" },
        "popupMedia": ""
      },
      "id": 84
    },
    {
      "geometry": {
        "type": "Point",
        "coordinates": [-34.8273320619, 35.6616210937]
      },
      "type": "Feature",
      "properties": {
        "popupTitle": { "en": "" },
        "popupContent": { "en": "" },
        "popupMedia": ""
      },
      "id": 85
    },
    {
      "geometry": {
        "type": "Point",
        "coordinates": [-34.4250361302, 36.8975830078]
      },
      "type": "Feature",
      "properties": {
        "popupTitle": { "en": "" },
        "popupContent": { "en": "" },
        "popupMedia": ""
      },
      "id": 86
    },
    {
      "geometry": {
        "type": "Point",
        "coordinates": [-33.086939259, 37.7600097656]
      },
      "type": "Feature",
      "properties": {
        "popupTitle": { "en": "" },
        "popupContent": { "en": "" },
        "popupMedia": ""
      },
      "id": 87
    },
    {
      "geometry": {
        "type": "Point",
        "coordinates": [-53.9496206177, 33.7994384765]
      },
      "type": "Feature",
      "properties": {
        "popupTitle": { "en": "" },
        "popupContent": { "en": "" },
        "popupMedia": ""
      },
      "id": 88
    },
    {
      "geometry": {
        "type": "Point",
        "coordinates": [-36.1641098939, 23.9275831851]
      },
      "type": "Feature",
      "properties": {
        "popupTitle": { "en": "" },
        "popupContent": { "en": "" },
        "popupMedia": ""
      },
      "id": 89
    },
    {
      "geometry": {
        "type": "Point",
        "coordinates": [-38.8384513145, 25.9821525904]
      },
      "type": "Feature",
      "properties": {
        "popupTitle": { "en": "" },
        "popupContent": { "en": "" },
        "popupMedia": ""
      },
      "id": 90
    },
    {
      "geometry": {
        "type": "Point",
        "coordinates": [-39.0317498943, 26.1374921804]
      },
      "type": "Feature",
      "properties": {
        "popupTitle": { "en": "" },
        "popupContent": { "en": "" },
        "popupMedia": ""
      },
      "id": 91
    },
    {
      "geometry": {
        "type": "Point",
        "coordinates": [-39.1101268811, 26.0908903034]
      },
      "type": "Feature",
      "properties": {
        "popupTitle": { "en": "" },
        "popupContent": { "en": "" },
        "popupMedia": ""
      },
      "id": 92
    },
    {
      "geometry": {
        "type": "Point",
        "coordinates": [-39.1796067118, 26.7191367071]
      },
      "type": "Feature",
      "properties": {
        "popupTitle": { "en": "" },
        "popupContent": { "en": "" },
        "popupMedia": ""
      },
      "id": 93
    },
    {
      "geometry": {
        "type": "Point",
        "coordinates": [-38.8425337271, 28.8171127473]
      },
      "type": "Feature",
      "properties": {
        "popupTitle": { "en": "" },
        "popupContent": { "en": "" },
        "popupMedia": ""
      },
      "id": 94
    },
    {
      "geometry": {
        "type": "Point",
        "coordinates": [-38.8253848943, 28.9050228157]
      },
      "type": "Feature",
      "properties": {
        "popupTitle": { "en": "" },
        "popupContent": { "en": "" },
        "popupMedia": ""
      },
      "id": 95
    },
    {
      "geometry": {
        "type": "Point",
        "coordinates": [-33.7346011365, 37.9353553121]
      },
      "type": "Feature",
      "properties": {
        "popupTitle": { "en": "" },
        "popupContent": { "en": "" },
        "popupMedia": ""
      },
      "id": 96
    },
    {
      "geometry": {
        "type": "Point",
        "coordinates": [-43.3443863229, 46.546760664]
      },
      "type": "Feature",
      "properties": {
        "popupTitle": { "en": "" },
        "popupContent": { "en": "" },
        "popupMedia": ""
      },
      "id": 97
    },
    {
      "geometry": {
        "type": "Point",
        "coordinates": [-43.1844404268, 46.546760664]
      },
      "type": "Feature",
      "properties": {
        "popupTitle": { "en": "" },
        "popupContent": { "en": "" },
        "popupMedia": ""
      },
      "id": 98
    },
    {
      "geometry": {
        "type": "Point",
        "coordinates": [-42.6214255453, 46.0854104959]
      },
      "type": "Feature",
      "properties": {
        "popupTitle": { "en": "" },
        "popupContent": { "en": "" },
        "popupMedia": ""
      },
      "id": 99
    },
    {
      "geometry": {
        "type": "Point",
        "coordinates": [-44.4450682918, 50.5304301648]
      },
      "type": "Feature",
      "properties": {
        "popupTitle": { "en": "" },
        "popupContent": { "en": "" },
        "popupMedia": ""
      },
      "id": 100
    },
    {
      "geometry": {
        "type": "Point",
        "coordinates": [-45.572945264, 49.5191205768]
      },
      "type": "Feature",
      "properties": {
        "popupTitle": { "en": "" },
        "popupContent": { "en": "" },
        "popupMedia": ""
      },
      "id": 101
    },
    {
      "geometry": {
        "type": "Point",
        "coordinates": [-46.3684082221, 44.4782099045]
      },
      "type": "Feature",
      "properties": {
        "popupTitle": { "en": "" },
        "popupContent": { "en": "" },
        "popupMedia": ""
      },
      "id": 102
    },
    {
      "geometry": {
        "type": "Point",
        "coordinates": [-62.6624653255, 1.9079370476]
      },
      "type": "Feature",
      "properties": {
        "popupTitle": { "en": "" },
        "popupContent": { "en": "" },
        "popupMedia": ""
      },
      "id": 103
    },
    {
      "geometry": {
        "type": "Point",
        "coordinates": [-56.2276940776, 30.0244206346]
      },
      "type": "Feature",
      "properties": {
        "popupTitle": { "en": "" },
        "popupContent": { "en": "" },
        "popupMedia": ""
      },
      "id": 104
    },
    {
      "geometry": {
        "type": "Point",
        "coordinates": [-56.2947902316, 29.964007712]
      },
      "type": "Feature",
      "properties": {
        "popupTitle": { "en": "" },
        "popupContent": { "en": "" },
        "popupMedia": ""
      },
      "id": 105
    },
    {
      "geometry": {
        "type": "Point",
        "coordinates": [-56.1635379542, 29.6180064279]
      },
      "type": "Feature",
      "properties": {
        "popupTitle": { "en": "" },
        "popupContent": { "en": "" },
        "popupMedia": ""
      },
      "id": 106
    },
    {
      "geometry": {
        "type": "Point",
        "coordinates": [-54.361646804, 27.245426194]
      },
      "type": "Feature",
      "properties": {
        "popupTitle": { "en": "" },
        "popupContent": { "en": "" },
        "popupMedia": ""
      },
      "id": 107
    },
    {
      "geometry": {
        "type": "Point",
        "coordinates": [-53.9403684754, 26.8335199034]
      },
      "type": "Feature",
      "properties": {
        "popupTitle": { "en": "" },
        "popupContent": { "en": "" },
        "popupMedia": ""
      },
      "id": 108
    },
    {
      "geometry": {
        "type": "Point",
        "coordinates": [-54.4415568325, 28.6513996659]
      },
      "type": "Feature",
      "properties": {
        "popupTitle": { "en": "" },
        "popupContent": { "en": "" },
        "popupMedia": ""
      },
      "id": 109
    },
    {
      "geometry": {
        "type": "Point",
        "coordinates": [-54.1777057646, 29.2897752811]
      },
      "type": "Feature",
      "properties": {
        "popupTitle": { "en": "" },
        "popupContent": { "en": "" },
        "popupMedia": ""
      },
      "id": 110
    },
    {
      "geometry": {
        "type": "Point",
        "coordinates": [-53.8873332161, 29.843182947]
      },
      "type": "Feature",
      "properties": {
        "popupTitle": { "en": "" },
        "popupContent": { "en": "" },
        "popupMedia": ""
      },
      "id": 111
    },
    {
      "geometry": {
        "type": "Point",
        "coordinates": [-53.80310342, 29.9255642051]
      },
      "type": "Feature",
      "properties": {
        "popupTitle": { "en": "" },
        "popupContent": { "en": "" },
        "popupMedia": ""
      },
      "id": 112
    },
    {
      "geometry": {
        "type": "Point",
        "coordinates": [-47.0095090473, 37.8470405612]
      },
      "type": "Feature",
      "properties": {
        "popupTitle": { "en": "" },
        "popupContent": { "en": "" },
        "popupMedia": ""
      },
      "id": 113
    },
    {
      "geometry": {
        "type": "Point",
        "coordinates": [-47.0506803782, 37.9184376516]
      },
      "type": "Feature",
      "properties": {
        "popupTitle": { "en": "" },
        "popupContent": { "en": "" },
        "popupMedia": ""
      },
      "id": 114
    },
    {
      "geometry": {
        "type": "Point",
        "coordinates": [-45.9849522905, 37.8581219458]
      },
      "type": "Feature",
      "properties": {
        "popupTitle": { "en": "" },
        "popupContent": { "en": "" },
        "popupMedia": ""
      },
      "id": 115
    },
    {
      "geometry": {
        "type": "Point",
        "coordinates": [-46.0688299555, 37.9624715395]
      },
      "type": "Feature",
      "properties": {
        "popupTitle": { "en": "" },
        "popupContent": { "en": "" },
        "popupMedia": ""
      },
      "id": 116
    },
    {
      "geometry": {
        "type": "Point",
        "coordinates": [-43.3136062998, 35.0294211421]
      },
      "type": "Feature",
      "properties": {
        "popupTitle": { "en": "" },
        "popupContent": { "en": "" },
        "popupMedia": ""
      },
      "id": 117
    },
    {
      "geometry": {
        "type": "Point",
        "coordinates": [-42.3084036813, 19.6975228007]
      },
      "type": "Feature",
      "properties": {
        "popupTitle": { "en": "" },
        "popupContent": { "en": "" },
        "popupMedia": ""
      },
      "id": 118
    },
    {
      "geometry": {
        "type": "Point",
        "coordinates": [-41.4633119766, 34.2718505859]
      },
      "type": "Feature",
      "properties": {
        "popupTitle": { "en": "" },
        "popupContent": { "en": "" },
        "popupMedia": ""
      },
      "id": 119
    },
    {
      "geometry": {
        "type": "Point",
        "coordinates": [-41.4756602002, 34.4201660156]
      },
      "type": "Feature",
      "properties": {
        "popupTitle": { "en": "" },
        "popupContent": { "en": "" },
        "popupMedia": ""
      },
      "id": 120
    },
    {
      "geometry": {
        "type": "Point",
        "coordinates": [-41.3932942887, 34.1564941406]
      },
      "type": "Feature",
      "properties": {
        "popupTitle": { "en": "" },
        "popupContent": { "en": "" },
        "popupMedia": ""
      },
      "id": 121
    },
    {
      "geometry": {
        "type": "Point",
        "coordinates": [-43.5711418476, 21.0435985995]
      },
      "type": "Feature",
      "properties": {
        "popupTitle": { "en": "" },
        "popupContent": { "en": "" },
        "popupMedia": ""
      },
      "id": 122
    },
    {
      "geometry": {
        "type": "Point",
        "coordinates": [-56.2293961613, 30.9647983912]
      },
      "type": "Feature",
      "properties": {
        "popupTitle": { "en": "" },
        "popupContent": { "en": "" },
        "popupMedia": ""
      },
      "id": 123
    },
    {
      "geometry": {
        "type": "Point",
        "coordinates": [-56.2751542658, 30.9647983912]
      },
      "type": "Feature",
      "properties": {
        "popupTitle": { "en": "" },
        "popupContent": { "en": "" },
        "popupMedia": ""
      },
      "id": 124
    },
    {
      "geometry": {
        "type": "Point",
        "coordinates": [-51.5422939514, 35.2157933715]
      },
      "type": "Feature",
      "properties": {
        "popupTitle": { "en": "" },
        "popupContent": { "en": "" },
        "popupMedia": ""
      },
      "id": 125
    }
  ]
}
