{
  "format": 2,
  "name": {
    "pt": "Fruto do Pôr do Sol",
    "en": "Sunsettia",
    "ru": "Закатник"
  },
  "description": {
    "en": "A plump fruit abundant across Teyvat. Used to craft Jam for Recipes."
  },
  "enabled": true,
  "cluster": "on",
  "respawn": "none",
  "icons": {
    "filter": "sunsettia",
    "base": {
      "marker": true
    },
    "done": {
      "marker": true
    }
  },
  "data": [
    {
      "coordinates": [-13.81927, 45.67343],
      "id": "F245023E6EEAE6E4FE98EAA0AB5F704B33F2AA4A",
      "importIds": {
        "gm_legacy": ["mondstadtSunsettia/1"]
      },
      "popupAttribution": "Yuanshen.site",
      "popupTitle": {
        "en": "MIGRATED MARKER: F4321C8"
      }
    },
    {
      "coordinates": [-15.38492, 44.57578],
      "id": "09F8ADBBEBC6504D1A4C78AE96AE460B22F80921",
      "importIds": {
        "gm_legacy": ["mondstadtSunsettia/2"]
      },
      "popupAttribution": "Yuanshen.site",
      "popupTitle": {
        "en": "MIGRATED MARKER: A155D30"
      }
    },
    {
      "coordinates": [-13.78745, 48.99766],
      "id": "3971C791313B2AAEDFC64B1B904A47746438DE1E",
      "importIds": {
        "gm_legacy": ["mondstadtSunsettia/3"]
      },
      "popupAttribution": "Yuanshen.site",
      "popupTitle": {
        "en": "MIGRATED MARKER: 4E75B7F"
      }
    },
    {
      "coordinates": [-16.52949, 44.26328],
      "id": "4F203ED10AE3AE78EA6E80DE33C67F21F9370267",
      "importIds": {
        "gm_legacy": ["mondstadtSunsettia/4"]
      },
      "popupAttribution": "Yuanshen.site",
      "popupTitle": {
        "en": "MIGRATED MARKER: 71BC3CB"
      }
    },
    {
      "coordinates": [-16.6037, 44.2711],
      "id": "B7CF13F6A25D87BF6AD5F8F7BA931FB19B287648",
      "importIds": {
        "gm_legacy": ["mondstadtSunsettia/5"]
      },
      "popupAttribution": "Yuanshen.site",
      "popupContent": {
        "en": "These ones are laying on the ground."
      },
      "popupTitle": {
        "en": "MIGRATED MARKER: 376E7FF"
      }
    },
    {
      "coordinates": [-15.9319, 44.96641],
      "id": "B8B385F20486B20ACFE5F637F25512F3B078628D",
      "importIds": {
        "gm_legacy": ["mondstadtSunsettia/6"]
      },
      "popupAttribution": "Yuanshen.site",
      "popupTitle": {
        "en": "MIGRATED MARKER: 2209098"
      }
    },
    {
      "coordinates": [-15.88112, 45.32969],
      "id": "0194A71451C496F966276D8A84DCE26854E4A65B",
      "importIds": {
        "gm_legacy": ["mondstadtSunsettia/7"]
      },
      "popupAttribution": "Yuanshen.site",
      "popupTitle": {
        "en": "MIGRATED MARKER: E09E7F5"
      }
    },
    {
      "coordinates": [-15.70146, 48.38828],
      "id": "584DCDA5C1064F3A3FAD5201C0B5EB310C6DD093",
      "importIds": {
        "gm_legacy": ["mondstadtSunsettia/8"]
      },
      "popupAttribution": "Yuanshen.site",
      "popupTitle": {
        "en": "MIGRATED MARKER: 3791BF1"
      }
    },
    {
      "coordinates": [-16.15062, 47.30234],
      "id": "50D2EB65C67A558CEB7AB74FE7F1C2095D4A3387",
      "importIds": {
        "gm_legacy": ["mondstadtSunsettia/9"]
      },
      "popupAttribution": "Yuanshen.site",
      "popupTitle": {
        "en": "MIGRATED MARKER: 9E2D07F"
      }
    },
    {
      "coordinates": [-17.16644, 46.35312],
      "id": "B77D4D215A75E98AD902966E17D37DED6DE8C2A3",
      "importIds": {
        "gm_legacy": ["mondstadtSunsettia/10"]
      },
      "popupAttribution": "Yuanshen.site",
      "popupTitle": {
        "en": "MIGRATED MARKER: F10233B"
      }
    },
    {
      "coordinates": [-17.79144, 45.90781],
      "id": "F2CE09B9A6DB29D0588422CB0D8F8BA27AD1AC9E",
      "importIds": {
        "gm_legacy": ["mondstadtSunsettia/11"]
      },
      "popupAttribution": "Yuanshen.site",
      "popupTitle": {
        "en": "MIGRATED MARKER: C4521D5"
      }
    },
    {
      "coordinates": [-17.52972, 45.23594],
      "id": "062F72F33CEA37CA311C0B6DECFE32086FB92F67",
      "importIds": {
        "gm_legacy": ["mondstadtSunsettia/12"]
      },
      "popupAttribution": "Yuanshen.site",
      "popupTitle": {
        "en": "MIGRATED MARKER: ACD1EF5"
      }
    },
    {
      "coordinates": [-17.55707, 45.04844],
      "id": "8071BB53386BFAC77684C00F47D60BF634B5660E",
      "importIds": {
        "gm_legacy": ["mondstadtSunsettia/13"]
      },
      "popupAttribution": "Yuanshen.site",
      "popupTitle": {
        "en": "MIGRATED MARKER: 326F6ED"
      }
    }
  ]
}
